{
    "0": {
        "sentence_x0": "وطالب بتعقب المجرمين والاقتصاص منهمءمتمنيا الا يكون مصير التحقيق عمليهالتفجير",
        "sentence_x10": "كبقيه جرائم الاغتيال السابقهتزال الساعه مجهوله المعالم والاهدافالسائقون العموميونواستنكر اتحاد",
        "sentence_x20": "نقابات سائقي السياراتالعموميه للنقل البري الاعتداء اصاباوتوبيسين واودي بمياه القتلي",
        "sentence_x30": "والجرحيالابرياء مطالبا باجراء التحقيق الفوري لكشفالقاعلين المجرمين القتله وانزال اشد",
        "sentence_x40": "العقوباتحقهم يندرج العدوان ضمنالاعمال المشابمه لاستشماد الرئيس رفيقالحريري ورفاقه الشهداء",
        "sentence_x50": "العابثه بالوطنمهدده السلم الاهلي والاستقرار العام\n",
        "keywords": "اغتيال,رفيق,الحريري",
        "year": 2007,
        "label": "",
        "sentence_0": "وطالب بتعقب المجرمين والاقتصاص منهمءمتمنيا الا يكون مصير التحقيق عمليهالتفجير",
        "sentence_10": "كبقيه جرائم الاغتيال السابقهتزال الساعه مجهوله المعالم والاهدافالسائقون العموميونواستنكر اتحاد",
        "sentence_20": "نقابات سائقي السياراتالعموميه للنقل البري الاعتداء اصاباوتوبيسين واودي بمياه القتلي",
        "sentence_30": "والجرحيالابرياء مطالبا باجراء التحقيق الفوري لكشفالقاعلين المجرمين القتله وانزال اشد",
        "sentence_40": "العقوباتحقهم يندرج العدوان ضمنالاعمال المشابمه لاستشماد الرئيس رفيقالحريري ورفاقه الشهداء",
        "sentence_50": "العابثه بالوطنمهدده السلم الاهلي والاستقرار العام\n"
    },
    "1": {
        "sentence_x0": "دول التحقيقالدولي قضيه اغتيال الرئيسارفيق الحريري نهد\n",
        "keywords": "اغتيال,رفيق,الحريري",
        "year": 2007,
        "label": "",
        "sentence_0": "دول التحقيقالدولي قضيه اغتيال الرئيسارفيق الحريري نهد\n"
    },
    "2": {
        "sentence_x0": "وتعرضت سوريا لضغوط دوليهشديده اغتيال رئيس الوزراءاللبناني السابق رفيق الحريري",
        "sentence_x10": "عامبيروت وجمهتاصابع الاتمام الي دمشقومي تسعي حاليا الي الخروجحال العزله",
        "sentence_x20": "فرضت عليما\n",
        "keywords": "اغتيال,رفيق,الحريري",
        "year": 2007,
        "label": "",
        "sentence_0": "وتعرضت سوريا لضغوط دوليهشديده اغتيال رئيس الوزراءاللبناني السابق رفيق الحريري",
        "sentence_10": "عامبيروت وجمهتاصابع الاتمام الي دمشقومي تسعي حاليا الي الخروجحال العزله",
        "sentence_20": "فرضت عليما\n"
    },
    "3": {
        "sentence_x0": "وقد يكون المفيد التذكير بان اللوبي اللبناني واشنطن خلالالاعداد للقرار",
        "sentence_x10": "المرحله التي تلت اقراره قبل اغتياللرئيس رفيق الحريري كان يواجه",
        "sentence_x20": "اللويب الاسرائيلي العاصمهالاميركيه عمل بلا كلل ملل تقويض القرارء واقناعالاداره",
        "sentence_x30": "الاميركيه بعدم التسرع دفع النظام السوري الي خارجلبنان\n",
        "keywords": "اغتيال,رفيق,الحريري",
        "year": 2007,
        "label": "",
        "sentence_0": "وقد يكون المفيد التذكير بان اللوبي اللبناني واشنطن خلالالاعداد للقرار",
        "sentence_10": "المرحله التي تلت اقراره قبل اغتياللرئيس رفيق الحريري كان يواجه",
        "sentence_20": "اللويب الاسرائيلي العاصمهالاميركيه عمل بلا كلل ملل تقويض القرارء واقناعالاداره",
        "sentence_30": "الاميركيه بعدم التسرع دفع النظام السوري الي خارجلبنان\n"
    },
    "4": {
        "sentence_x0": "يخشاه الاوساطيؤدي رفع الشغوط العربيه سوريا اليتكمل تعيد نهجها التعاطي",
        "sentence_x10": "ولبنانحدث الانفتاح السعودي قبل عاموبعد اشهر قليله اغتيال الرئيس رفيقالحريري\n",
        "keywords": "اغتيال,رفيق,الحريري",
        "year": 2007,
        "label": "",
        "sentence_0": "يخشاه الاوساطيؤدي رفع الشغوط العربيه سوريا اليتكمل تعيد نهجها التعاطي",
        "sentence_10": "ولبنانحدث الانفتاح السعودي قبل عاموبعد اشهر قليله اغتيال الرئيس رفيقالحريري\n"
    },
    "5": {
        "sentence_x0": "تفاؤل حذر بددمشاعر الفلفاستعادت البورصه معظم خسائرهاكتب ايلي قهوجيشهدت الاسواق",
        "sentence_x10": "الماليه اللبنانيهالارتياح اواخر الاسبوعالماضي المواقف الداعمهلمشاريع التسويه السياسيهللازمه عبرت عنها",
        "sentence_x20": "خطبالاقطاب الفاعلين داخل الاكثريهالحاكمه الذكري السنويهالثانيه لاغتيال الرئيس رفيقالحريري\n",
        "keywords": "اغتيال,رفيق,الحريري",
        "year": 2007,
        "label": "",
        "sentence_0": "تفاؤل حذر بددمشاعر الفلفاستعادت البورصه معظم خسائرهاكتب ايلي قهوجيشهدت الاسواق",
        "sentence_10": "الماليه اللبنانيهالارتياح اواخر الاسبوعالماضي المواقف الداعمهلمشاريع التسويه السياسيهللازمه عبرت عنها",
        "sentence_20": "خطبالاقطاب الفاعلين داخل الاكثريهالحاكمه الذكري السنويهالثانيه لاغتيال الرئيس رفيقالحريري\n"
    },
    "6": {
        "sentence_x0": "علق ذكري الحريري وجريمه عين علقغانم يريدون لبنان ساحه عراقيهاللبنائيين",
        "sentence_x10": "يزدادون مناعهالذكري الثائيه لاغتيالالرئيس رفيق المريري اصدرالنائب روبير غانم البيان",
        "sentence_x20": "الاتيالغائب الحاضر بينناءيفتقده لبنان الذكري الثانيهلاستشماده اكثر اي وقتمضي\n",
        "keywords": "اغتيال,رفيق,الحريري",
        "year": 2007,
        "label": "",
        "sentence_0": "علق ذكري الحريري وجريمه عين علقغانم يريدون لبنان ساحه عراقيهاللبنائيين",
        "sentence_10": "يزدادون مناعهالذكري الثائيه لاغتيالالرئيس رفيق المريري اصدرالنائب روبير غانم البيان",
        "sentence_20": "الاتيالغائب الحاضر بينناءيفتقده لبنان الذكري الثانيهلاستشماده اكثر اي وقتمضي\n"
    },
    "7": {
        "sentence_x0": "يحمل الكاتب مسؤوليه اغتيال الرئيس رفيقالحريري لسوريا وانما يعتبر الراي",
        "sentence_x10": "العام اللبناني اتخذ الموقف وانالتظامرات الاحتجاجيه الضخمه جرت اذار بالاضافه",
        "sentence_x20": "الي الضغوطالدوليه يسبق مثيل كانت وراء الانسحاب الممين للقوات السوريهيسان",
        "sentence_x30": "العام يعتبره نهايه حقبه\n",
        "keywords": "اغتيال,رفيق,الحريري",
        "year": 2007,
        "label": "",
        "sentence_0": "يحمل الكاتب مسؤوليه اغتيال الرئيس رفيقالحريري لسوريا وانما يعتبر الراي",
        "sentence_10": "العام اللبناني اتخذ الموقف وانالتظامرات الاحتجاجيه الضخمه جرت اذار بالاضافه",
        "sentence_20": "الي الضغوطالدوليه يسبق مثيل كانت وراء الانسحاب الممين للقوات السوريهيسان",
        "sentence_30": "العام يعتبره نهايه حقبه\n"
    },
    "8": {
        "sentence_x0": "ذكري الحريريوعشيه الذكري الثانيه لاغتيال الرئيس رفيق الحريري تصادفغد الاربعاء",
        "sentence_x10": "وانسجاما اعلان الحكومه اليوم يوم حداد وطنيتقفل المؤسسات العامه استجابت",
        "sentence_x20": "الميئات الاقتصاديه للموقفالرسمي وستلتزم الاقفال الرسمي القطاعات الاقتصاديه والصناعيهوالمصرفيه\n",
        "keywords": "اغتيال,رفيق,الحريري",
        "year": 2007,
        "label": "",
        "sentence_0": "ذكري الحريريوعشيه الذكري الثانيه لاغتيال الرئيس رفيق الحريري تصادفغد الاربعاء",
        "sentence_10": "وانسجاما اعلان الحكومه اليوم يوم حداد وطنيتقفل المؤسسات العامه استجابت",
        "sentence_20": "الميئات الاقتصاديه للموقفالرسمي وستلتزم الاقفال الرسمي القطاعات الاقتصاديه والصناعيهوالمصرفيه\n"
    },
    "9": {
        "sentence_x0": "ايها اللبئناتيون وطنكم كانمدفا لمؤامره كبيره يزالءاغتيال الرئيس الشميد رفيقالحريري\n",
        "keywords": "اغتيال,رفيق,الحريري",
        "year": 2007,
        "label": "",
        "sentence_0": "ايها اللبئناتيون وطنكم كانمدفا لمؤامره كبيره يزالءاغتيال الرئيس الشميد رفيقالحريري\n"
    },
    "10": {
        "sentence_x0": "شار ار اخيرا الي ان رئيس لجنهالتحقيق الدوليه جريمهاغتيال الرئيس",
        "sentence_x10": "رفيق الحريريالقاضي برامرتس قامامس بزياره خاطفه لسوريالمتدم اربع ساعات\n",
        "keywords": "اغتيال,رفيق,الحريري",
        "year": 2007,
        "label": "",
        "sentence_0": "شار ار اخيرا الي ان رئيس لجنهالتحقيق الدوليه جريمهاغتيال الرئيس",
        "sentence_10": "رفيق الحريريالقاضي برامرتس قامامس بزياره خاطفه لسوريالمتدم اربع ساعات\n"
    },
    "11": {
        "sentence_x0": "العكس تريبدمعرفه الحقيقه يمكن انترقض انشاء المحكمه وان يعرفقتل الرئيس",
        "sentence_x10": "الشهيد رفيقالرئيش السنيوره مطار ماركا العسكريالحريري وكل الاغتيالاتحصلت\n",
        "keywords": "اغتيال,رفيق,الحريري",
        "year": 2007,
        "label": "",
        "sentence_0": "العكس تريبدمعرفه الحقيقه يمكن انترقض انشاء المحكمه وان يعرفقتل الرئيس",
        "sentence_10": "الشهيد رفيقالرئيش السنيوره مطار ماركا العسكريالحريري وكل الاغتيالاتحصلت\n"
    },
    "12": {
        "sentence_x0": "وسال سر الصمتالمريب الاكثريه الممايونيهحول تمنع الدولالتعاون لجنه التحقيق الدوليهجريمه",
        "sentence_x10": "اغتيال الرئيس رفيقالحريري ان الدول كانتتحمل شعار كشف الحقيقهوسار ركابهايتاجرون",
        "sentence_x20": "بالدماء\n",
        "keywords": "اغتيال,رفيق,الحريري",
        "year": 2007,
        "label": "",
        "sentence_0": "وسال سر الصمتالمريب الاكثريه الممايونيهحول تمنع الدولالتعاون لجنه التحقيق الدوليهجريمه",
        "sentence_10": "اغتيال الرئيس رفيقالحريري ان الدول كانتتحمل شعار كشف الحقيقهوسار ركابهايتاجرون",
        "sentence_20": "بالدماء\n"
    },
    "13": {
        "sentence_x0": "امله تتحول الذكري الثانيه وراي رئيس جمعيه تجار بيروتلاستشماد الرئيس",
        "sentence_x10": "رفيق الحريري نديم عاصي ان الذكري السنويهمناسبه للتوحد حول لبتان",
        "sentence_x20": "ونبذ الثانيه لاغتيال الرئيس الشهيدالفتنه وان تشكل مدخلا رفيق الحريري",
        "sentence_x30": "تحل السنهتلاقي اللبنانيين وااتفاقممحل المشكلات القائمه والابتعادمسببات الانقسام الماصل\n",
        "keywords": "اغتيال,رفيق,الحريري",
        "year": 2007,
        "label": "",
        "sentence_0": "امله تتحول الذكري الثانيه وراي رئيس جمعيه تجار بيروتلاستشماد الرئيس",
        "sentence_10": "رفيق الحريري نديم عاصي ان الذكري السنويهمناسبه للتوحد حول لبتان",
        "sentence_20": "ونبذ الثانيه لاغتيال الرئيس الشهيدالفتنه وان تشكل مدخلا رفيق الحريري",
        "sentence_30": "تحل السنهتلاقي اللبنانيين وااتفاقممحل المشكلات القائمه والابتعادمسببات الانقسام الماصل\n"
    },
    "14": {
        "sentence_x0": "الطبيعي ان يلاحق قتله الرئيسرفيق الحريري والمسؤولونالاغتيالات ال الاخري ويحاكمواللعداله",
        "sentence_x10": "والردع ايضا\n",
        "keywords": "اغتيال,رفيق,الحريري",
        "year": 2007,
        "label": "",
        "sentence_0": "الطبيعي ان يلاحق قتله الرئيسرفيق الحريري والمسؤولونالاغتيالات ال الاخري ويحاكمواللعداله",
        "sentence_10": "والردع ايضا\n"
    },
    "15": {
        "sentence_x0": "وخصوصا المحكمهالفصل تتمكناستدعاء الشهود والمتورطينجريمه اغتيال الرئيس الشهيدرفيق الحريري\n",
        "keywords": "اغتيال,رفيق,الحريري",
        "year": 2007,
        "label": "",
        "sentence_0": "وخصوصا المحكمهالفصل تتمكناستدعاء الشهود والمتورطينجريمه اغتيال الرئيس الشهيدرفيق الحريري\n"
    },
    "16": {
        "sentence_x0": "يجب ان يكون مستعدالمتابعه المحكمه الدوليه وضمانسير العداله وتنفيذ الاحكامحق",
        "sentence_x10": "تثبت ادائتهماغتيال رئيس الحكومهالسابق رفيق الحريري وبقيهشهداء ثوره بصحث\n",
        "keywords": "اغتيال,رفيق,الحريري",
        "year": 2007,
        "label": "",
        "sentence_0": "يجب ان يكون مستعدالمتابعه المحكمه الدوليه وضمانسير العداله وتنفيذ الاحكامحق",
        "sentence_10": "تثبت ادائتهماغتيال رئيس الحكومهالسابق رفيق الحريري وبقيهشهداء ثوره بصحث\n"
    },
    "17": {
        "sentence_x0": "وبفضل التقدماحرز الاشهر الاربعه الاخيره باتت اللجنهقادره وضع خلاصات اوليه",
        "sentence_x10": "شانعدد مهم اوجه التحقيق اغتيال رقيقالحريري مسائل متعلقه بفحصموقع الجريمه",
        "sentence_x20": "ونوع المتفشجرات المستخدمهوفان الميتسوبيشي كانتر استخدمالمجومء الافراد الضالعين مراقبهرفيق الحريري\n",
        "keywords": "اغتيال,رفيق,الحريري",
        "year": 2007,
        "label": "",
        "sentence_0": "وبفضل التقدماحرز الاشهر الاربعه الاخيره باتت اللجنهقادره وضع خلاصات اوليه",
        "sentence_10": "شانعدد مهم اوجه التحقيق اغتيال رقيقالحريري مسائل متعلقه بفحصموقع الجريمه",
        "sentence_20": "ونوع المتفشجرات المستخدمهوفان الميتسوبيشي كانتر استخدمالمجومء الافراد الضالعين مراقبهرفيق الحريري\n"
    },
    "18": {
        "sentence_x0": "شان محاكمه حزبالله تزيد خطوط التصدع وتعتقها مجتمع يكافح اجل",
        "sentence_x10": "التعاطيالمحاوله الحاليه لمحاكمه المذنبين اغتيال رئيس الوزراء السابقرفيق الحريري\n",
        "keywords": "اغتيال,رفيق,الحريري",
        "year": 2007,
        "label": "",
        "sentence_0": "شان محاكمه حزبالله تزيد خطوط التصدع وتعتقها مجتمع يكافح اجل",
        "sentence_10": "التعاطيالمحاوله الحاليه لمحاكمه المذنبين اغتيال رئيس الوزراء السابقرفيق الحريري\n"
    },
    "19": {
        "sentence_x0": "ورغم الصوره القاتمه اوجز يشمده لبناناغتيال الرئيس رفيق الحريري لغايه",
        "sentence_x10": "المازق السياسيالراهنء اكد ان النظام المصرفي يبرهن قدره رائعهمواجهه المصاعب",
        "sentence_x20": "والتكيف معما بنجاح وقد اصبحتالسمه خصائصه البنيويه مشيرا السياقالي تغلبه",
        "sentence_x30": "الصدمات الحقيقيه ومي اشد بكثيرتتصورها نماذج المحاكاه تصممماوكالات التصنيف والمؤسسات",
        "sentence_x40": "الدوليه اطار نماذجماالاقتصاديه الكليه\n",
        "keywords": "اغتيال,رفيق,الحريري",
        "year": 2007,
        "label": "",
        "sentence_0": "ورغم الصوره القاتمه اوجز يشمده لبناناغتيال الرئيس رفيق الحريري لغايه",
        "sentence_10": "المازق السياسيالراهنء اكد ان النظام المصرفي يبرهن قدره رائعهمواجهه المصاعب",
        "sentence_20": "والتكيف معما بنجاح وقد اصبحتالسمه خصائصه البنيويه مشيرا السياقالي تغلبه",
        "sentence_30": "الصدمات الحقيقيه ومي اشد بكثيرتتصورها نماذج المحاكاه تصممماوكالات التصنيف والمؤسسات",
        "sentence_40": "الدوليه اطار نماذجماالاقتصاديه الكليه\n"
    },
    "20": {
        "sentence_x0": "النظام السوريء وبعد مسارعته الي سحب جيشه النظاميجريمه اغتيال رفيق",
        "sentence_x10": "الحريري سارع ايضا الي اعداد عده الثاربينها بالطبع “فتح الاسلام",
        "sentence_x20": "الي علق عين علق وجريالقبض طرف الحبل اصبح عهده لجنه",
        "sentence_x30": "التحقيقالدوليه\n",
        "keywords": "اغتيال,رفيق,الحريري",
        "year": 2007,
        "label": "",
        "sentence_0": "النظام السوريء وبعد مسارعته الي سحب جيشه النظاميجريمه اغتيال رفيق",
        "sentence_10": "الحريري سارع ايضا الي اعداد عده الثاربينها بالطبع “فتح الاسلام",
        "sentence_20": "الي علق عين علق وجريالقبض طرف الحبل اصبح عهده لجنه",
        "sentence_30": "التحقيقالدوليه\n"
    },
    "21": {
        "sentence_x0": "ان قوي المعارضه تشك يوما ان المحكمه الدوليه ستكونسياسيه وكيديه",
        "sentence_x10": "وانتقاميه بامتيازء وهي المقابل تصل اليشيء يتعلق بمهمتها الاساسيه وهي",
        "sentence_x20": "كشف يقف وراء جريمهاغتيال الرئيس رفيق الحريري\n",
        "keywords": "اغتيال,رفيق,الحريري",
        "year": 2007,
        "label": "",
        "sentence_0": "ان قوي المعارضه تشك يوما ان المحكمه الدوليه ستكونسياسيه وكيديه",
        "sentence_10": "وانتقاميه بامتيازء وهي المقابل تصل اليشيء يتعلق بمهمتها الاساسيه وهي",
        "sentence_20": "كشف يقف وراء جريمهاغتيال الرئيس رفيق الحريري\n"
    },
    "22": {
        "sentence_x0": "واليالان يعلمنا احد الموادتسيس المحكمهقرارات التشفي والانتقاموالتسييس اتخذما مجلسالامن وجل",
        "sentence_x10": "نريده معرفهحاول اغتيال مروان حمادهاغتال الرئيس رفيق الحريريوصولا الي اغتيال",
        "sentence_x20": "نجلي بيارءلاسباب عائليه انما رحمه بالعبادولوقف الاعمال الاجراميه حقالوطن وفتح",
        "sentence_x30": "صفحه جديدهالامن والاستقرار لبنان\n",
        "keywords": "اغتيال,رفيق,الحريري",
        "year": 2007,
        "label": "",
        "sentence_0": "واليالان يعلمنا احد الموادتسيس المحكمهقرارات التشفي والانتقاموالتسييس اتخذما مجلسالامن وجل",
        "sentence_10": "نريده معرفهحاول اغتيال مروان حمادهاغتال الرئيس رفيق الحريريوصولا الي اغتيال",
        "sentence_20": "نجلي بيارءلاسباب عائليه انما رحمه بالعبادولوقف الاعمال الاجراميه حقالوطن وفتح",
        "sentence_30": "صفحه جديدهالامن والاستقرار لبنان\n"
    },
    "23": {
        "sentence_x0": "غضون عقد مجلسالامن جلسه مفتوحه امسنيويورك استمع الي رئيسلجنه التحقيق",
        "sentence_x10": "الدوليه جريمهاغتيال الرئيس رفيق الحريريالقاضي البلجيكي سيرج برامرتسعرض التقرير الثامن",
        "sentence_x20": "للجنهاعمالها\n",
        "keywords": "اغتيال,رفيق,الحريري",
        "year": 2007,
        "label": "",
        "sentence_0": "غضون عقد مجلسالامن جلسه مفتوحه امسنيويورك استمع الي رئيسلجنه التحقيق",
        "sentence_10": "الدوليه جريمهاغتيال الرئيس رفيق الحريريالقاضي البلجيكي سيرج برامرتسعرض التقرير الثامن",
        "sentence_20": "للجنهاعمالها\n"
    },
    "24": {
        "sentence_x0": "ان الحكومه تتقدم باعمالهاالي اللبنانيين تريد تذكربانها حرصت حمايه التحقيقالدولي",
        "sentence_x10": "جريمه اغتيال الرئيسالشهيد رفيق الحريري ورفاقهرغم الضغوط والتهديدات\n",
        "keywords": "اغتيال,رفيق,الحريري",
        "year": 2007,
        "label": "",
        "sentence_0": "ان الحكومه تتقدم باعمالهاالي اللبنانيين تريد تذكربانها حرصت حمايه التحقيقالدولي",
        "sentence_10": "جريمه اغتيال الرئيسالشهيد رفيق الحريري ورفاقهرغم الضغوط والتهديدات\n"
    },
    "25": {
        "sentence_x0": "السلماغتيال الرئيس رفيق الحريري وسائر\n",
        "keywords": "اغتيال,رفيق,الحريري",
        "year": 2007,
        "label": "",
        "sentence_0": "السلماغتيال الرئيس رفيق الحريري وسائر\n"
    },
    "26": {
        "sentence_x0": "الحادثه الاولي الكبري سلسله مواقف حزب الله جرتصور تجمع السيد",
        "sentence_x10": "حسن نصرائله والرئيسين حافظ وبشار الاسد وباسل الاسدتظاهرات السوريين اب",
        "sentence_x20": "الارشيفمشهد لمتظاهرين سوريين دمشق اذاراذار حيتما سيز تظامره خوفه الانسحاب",
        "sentence_x30": "المرتقب لججيشمحاوله اغتيال الوزير مروان حماده ومرورا بسلسله الاغتيالات السياسيه",
        "sentence_x40": "المتعاقبه هرت لبنان بعدما انعطف اغتيالالرئيس رفيق الحريري انعطافا تاريخيا",
        "sentence_x50": "مشهوداء تتجاوز مواقف هزب الله اعلانه الشجب الرسمي واللفظي لهذه",
        "sentence_x60": "الاغتيالات\n",
        "keywords": "اغتيال,رفيق,الحريري",
        "year": 2007,
        "label": "",
        "sentence_0": "الحادثه الاولي الكبري سلسله مواقف حزب الله جرتصور تجمع السيد",
        "sentence_10": "حسن نصرائله والرئيسين حافظ وبشار الاسد وباسل الاسدتظاهرات السوريين اب",
        "sentence_20": "الارشيفمشهد لمتظاهرين سوريين دمشق اذاراذار حيتما سيز تظامره خوفه الانسحاب",
        "sentence_30": "المرتقب لججيشمحاوله اغتيال الوزير مروان حماده ومرورا بسلسله الاغتيالات السياسيه",
        "sentence_40": "المتعاقبه هرت لبنان بعدما انعطف اغتيالالرئيس رفيق الحريري انعطافا تاريخيا",
        "sentence_50": "مشهوداء تتجاوز مواقف هزب الله اعلانه الشجب الرسمي واللفظي لهذه",
        "sentence_60": "الاغتيالات\n"
    },
    "27": {
        "sentence_x0": "وثقتنا كبيره دائما بهذا الدور وان بلاده ضد انشاء المحكمه",
        "sentence_x10": "ولم يخمم منما ان دمشق ترغب التقاوض حولماء وحتي اجل",
        "sentence_x20": "معاوده الحوار الولايات تكشف اماكن وجود اساحهان حل الازمه السياسيه",
        "sentence_x30": "لبنان ان القاده يدركون انه عندما تكون الطابع الدولي جريمه",
        "sentence_x40": "اغتيال الرئيس رفيق الحريري باعتبار انها كانت تتمسك بمقوله رفض",
        "sentence_x50": "المحكمه وعدم المتحده حول العراق قضايا اخري المنطقه\n",
        "keywords": "اغتيال,رفيق,الحريري",
        "year": 2007,
        "label": "",
        "sentence_0": "وثقتنا كبيره دائما بهذا الدور وان بلاده ضد انشاء المحكمه",
        "sentence_10": "ولم يخمم منما ان دمشق ترغب التقاوض حولماء وحتي اجل",
        "sentence_20": "معاوده الحوار الولايات تكشف اماكن وجود اساحهان حل الازمه السياسيه",
        "sentence_30": "لبنان ان القاده يدركون انه عندما تكون الطابع الدولي جريمه",
        "sentence_40": "اغتيال الرئيس رفيق الحريري باعتبار انها كانت تتمسك بمقوله رفض",
        "sentence_50": "المحكمه وعدم المتحده حول العراق قضايا اخري المنطقه\n"
    },
    "28": {
        "sentence_x0": "الانقلاب الوحيد سياسهفرنساحيال احي فا عمدالرئيس نيكولا ساركوزي يتمثلبالانفتاح المعارضه",
        "sentence_x10": "بقياده حزب الله والتحاورالجدي معها اجل تشجيعها ودفعها الي التلاقيالغالبيه",
        "sentence_x20": "النتيابيه بهدف تدعيم استقلال لبنان وسيادتهووحدته الوطنيه والسلم الااهلي ومعالجه",
        "sentence_x30": "مشاكلهالحاده عبر الحوار وليس عبر الضغوط والتمديداتبعيدا هيمنه سوريه وبما",
        "sentence_x40": "يساعد مواصلهتطبيق قرارات مجلس الامن الدولي الصله وعليتسميل عمل المحكمه",
        "sentence_x50": "الدوليه المكلفه النظرجريمه اغتيال الرئيس رفيق الحريري ورفاقه وفي جراكمسياسيه",
        "sentence_x60": "اخري مرتبطه بها\n",
        "keywords": "اغتيال,رفيق,الحريري",
        "year": 2007,
        "label": "",
        "sentence_0": "الانقلاب الوحيد سياسهفرنساحيال احي فا عمدالرئيس نيكولا ساركوزي يتمثلبالانفتاح المعارضه",
        "sentence_10": "بقياده حزب الله والتحاورالجدي معها اجل تشجيعها ودفعها الي التلاقيالغالبيه",
        "sentence_20": "النتيابيه بهدف تدعيم استقلال لبنان وسيادتهووحدته الوطنيه والسلم الااهلي ومعالجه",
        "sentence_30": "مشاكلهالحاده عبر الحوار وليس عبر الضغوط والتمديداتبعيدا هيمنه سوريه وبما",
        "sentence_40": "يساعد مواصلهتطبيق قرارات مجلس الامن الدولي الصله وعليتسميل عمل المحكمه",
        "sentence_50": "الدوليه المكلفه النظرجريمه اغتيال الرئيس رفيق الحريري ورفاقه وفي جراكمسياسيه",
        "sentence_60": "اخري مرتبطه بها\n"
    },
    "29": {
        "sentence_x0": "ودعا سولاناء اجتماعه الرئيسالمصري حسني مبارك القاهره الي مخرجللمازق السياسي",
        "sentence_x10": "لبتانء مبرزا ضرورهتسويه مسالتي حكومه الوحده الوطنيهوالمحكمه الطابع الدولي لمحاكمهالمتهمين",
        "sentence_x20": "باغتيال رئيس الوزراء السابقرفيق الحريري\n",
        "keywords": "اغتيال,رفيق,الحريري",
        "year": 2007,
        "label": "",
        "sentence_0": "ودعا سولاناء اجتماعه الرئيسالمصري حسني مبارك القاهره الي مخرجللمازق السياسي",
        "sentence_10": "لبتانء مبرزا ضرورهتسويه مسالتي حكومه الوحده الوطنيهوالمحكمه الطابع الدولي لمحاكمهالمتهمين",
        "sentence_20": "باغتيال رئيس الوزراء السابقرفيق الحريري\n"
    },
    "30": {
        "sentence_x0": "وتطالب بكشفاقدموا اغتيال الرئيسالشهيد رفيق الحريري ومعاقبتهم\n",
        "keywords": "اغتيال,رفيق,الحريري",
        "year": 2007,
        "label": "",
        "sentence_0": "وتطالب بكشفاقدموا اغتيال الرئيسالشهيد رفيق الحريري ومعاقبتهم\n"
    },
    "31": {
        "sentence_x0": "وشدد حرص سوريادعم الحوار الاطراف اللبنانيينوصولا توافق تاليفحكومه وحده وطنيه",
        "sentence_x10": "يكونجدول اعمالها موضوع المحكمهالطابع الدولي لمن يثبتتورطهم جريمه اغتيال رئيسالوزراء",
        "sentence_x20": "اللبناني الراحل رفيقالحريريء داعيا الدول العربيهوالمجتمع الدولي الي دعميتوصل اليه",
        "sentence_x30": "اللبنائيون\n",
        "keywords": "اغتيال,رفيق,الحريري",
        "year": 2007,
        "label": "",
        "sentence_0": "وشدد حرص سوريادعم الحوار الاطراف اللبنانيينوصولا توافق تاليفحكومه وحده وطنيه",
        "sentence_10": "يكونجدول اعمالها موضوع المحكمهالطابع الدولي لمن يثبتتورطهم جريمه اغتيال رئيسالوزراء",
        "sentence_20": "اللبناني الراحل رفيقالحريريء داعيا الدول العربيهوالمجتمع الدولي الي دعميتوصل اليه",
        "sentence_30": "اللبنائيون\n"
    },
    "32": {
        "sentence_x0": "وقدطلبت انذاك الجميع ياتواءولم يتجاوبواء كان قبل اغتيالالرئيس الشميد رفيق",
        "sentence_x10": "الحريري\n",
        "keywords": "اغتيال,رفيق,الحريري",
        "year": 2007,
        "label": "",
        "sentence_0": "وقدطلبت انذاك الجميع ياتواءولم يتجاوبواء كان قبل اغتيالالرئيس الشميد رفيق",
        "sentence_10": "الحريري\n"
    },
    "33": {
        "sentence_x0": "السفير السويسري زاره وحذر هشاشه الوضعجعجع لبنان امش الحاجه دثوره",
        "sentence_x10": "الارز للواجهه الاطماع السودوالاجرام والتخويفوجه رئيس الميئه التنفيذيهلحزب القوات اللبنانيه",
        "sentence_x20": "سميرجعجع امس نداء الي اللينانيينالذكري الثانيه لاغتيال الرئيسرفيق الحريري دعاهم",
        "sentence_x30": "اليالمشاركه الكثيفه الذكريالسنويه الثانيه لانطلاق انتفاضهالاستقلال لافتا الي لبنانلايزال امس",
        "sentence_x40": "الحاجه الي ثورهالارز البيضاء مواجهه الاطماعالسودء الي روح الحريه والاستقلالوالدوله",
        "sentence_x50": "الفعليه القويه القادرهمواجمه تحويل لبنان ساحاتمواجهات داميه تنتمي\n",
        "keywords": "اغتيال,رفيق,الحريري",
        "year": 2007,
        "label": "",
        "sentence_0": "السفير السويسري زاره وحذر هشاشه الوضعجعجع لبنان امش الحاجه دثوره",
        "sentence_10": "الارز للواجهه الاطماع السودوالاجرام والتخويفوجه رئيس الميئه التنفيذيهلحزب القوات اللبنانيه",
        "sentence_20": "سميرجعجع امس نداء الي اللينانيينالذكري الثانيه لاغتيال الرئيسرفيق الحريري دعاهم",
        "sentence_30": "اليالمشاركه الكثيفه الذكريالسنويه الثانيه لانطلاق انتفاضهالاستقلال لافتا الي لبنانلايزال امس",
        "sentence_40": "الحاجه الي ثورهالارز البيضاء مواجهه الاطماعالسودء الي روح الحريه والاستقلالوالدوله",
        "sentence_50": "الفعليه القويه القادرهمواجمه تحويل لبنان ساحاتمواجهات داميه تنتمي\n"
    },
    "34": {
        "sentence_x0": "ودعا الناطق باسم وزاره الخارجيهالايراني محمد علي حسينيدرس ملف اغتيال",
        "sentence_x10": "رئيس الوزراءاللبنائي السابق رفيق الحريريبعيدا الاغراض السياسيهوكان الرئيس الايراني يتحدثلقاء",
        "sentence_x20": "وصحافيين اجانب وقالالكيان القاصب للقدسيفكر تكرار جرائمه وارتكبها العام الماضيالمسلمين",
        "sentence_x30": "لبنان\n",
        "keywords": "اغتيال,رفيق,الحريري",
        "year": 2007,
        "label": "",
        "sentence_0": "ودعا الناطق باسم وزاره الخارجيهالايراني محمد علي حسينيدرس ملف اغتيال",
        "sentence_10": "رئيس الوزراءاللبنائي السابق رفيق الحريريبعيدا الاغراض السياسيهوكان الرئيس الايراني يتحدثلقاء",
        "sentence_20": "وصحافيين اجانب وقالالكيان القاصب للقدسيفكر تكرار جرائمه وارتكبها العام الماضيالمسلمين",
        "sentence_30": "لبنان\n"
    },
    "35": {
        "sentence_x0": "تنظم جمعيه بيروت للتنميه الذكري الثانيه لاغتيال الرئيسرفيق الحريري ورفاقه",
        "sentence_x10": "دوره الشطرتج السريع لجميع الفثاتالعمريه نادي جمعيه متخرجي جامعه بيروت",
        "sentence_x20": "العربيه شارع حمديوم الاحد شباط\n",
        "keywords": "اغتيال,رفيق,الحريري",
        "year": 2007,
        "label": "",
        "sentence_0": "تنظم جمعيه بيروت للتنميه الذكري الثانيه لاغتيال الرئيسرفيق الحريري ورفاقه",
        "sentence_10": "دوره الشطرتج السريع لجميع الفثاتالعمريه نادي جمعيه متخرجي جامعه بيروت",
        "sentence_20": "العربيه شارع حمديوم الاحد شباط\n"
    },
    "36": {
        "sentence_x0": "كجنه التحقيق اغتيالالرئيس رفيق الحريري تستطيعالان متابعه عملها بكل همدوء",
        "sentence_x10": "لانالاستمرار سيكون مؤمنا خلاللجنه التحقيق الدوليه جهه ءوالمحكمه ستستكمل العمليهعتدما",
        "sentence_x20": "ستشكل\n",
        "keywords": "اغتيال,رفيق,الحريري",
        "year": 2007,
        "label": "",
        "sentence_0": "كجنه التحقيق اغتيالالرئيس رفيق الحريري تستطيعالان متابعه عملها بكل همدوء",
        "sentence_10": "لانالاستمرار سيكون مؤمنا خلاللجنه التحقيق الدوليه جهه ءوالمحكمه ستستكمل العمليهعتدما",
        "sentence_20": "ستشكل\n"
    },
    "37": {
        "sentence_x0": "ويعلم الكاتب انني اثرتكليفي تشكيل الحكومه انفقتاسبوعا كاملا الاتصالات والمشاوراتوبذل",
        "sentence_x10": "الجهد غبطه البطريرك صفيرومع اقطاب المعارضه يومهااهدي الي اللبناتيين حكومه",
        "sentence_x20": "اتحادوطنيء انني اوفق جهوديقلم يكن بالامكان احسنثالثاء افهم ايضا المقصود",
        "sentence_x30": "القولانني استقلت واققا اغتيال الرئيسالشهيد رفيق الحريري\n",
        "keywords": "اغتيال,رفيق,الحريري",
        "year": 2007,
        "label": "",
        "sentence_0": "ويعلم الكاتب انني اثرتكليفي تشكيل الحكومه انفقتاسبوعا كاملا الاتصالات والمشاوراتوبذل",
        "sentence_10": "الجهد غبطه البطريرك صفيرومع اقطاب المعارضه يومهااهدي الي اللبناتيين حكومه",
        "sentence_20": "اتحادوطنيء انني اوفق جهوديقلم يكن بالامكان احسنثالثاء افهم ايضا المقصود",
        "sentence_30": "القولانني استقلت واققا اغتيال الرئيسالشهيد رفيق الحريري\n"
    },
    "38": {
        "sentence_x0": "اغتيال الرئيس الشميد رفيق الحريري خير معين وحاضنومساعد للطائفه الشيعيه",
        "sentence_x10": "ويكفي نذكر المؤسساتا الليبي وكثير المواقف المشهوده بحيث كانت تعتبرشهودا",
        "sentence_x20": "باعمالنا وكلامنا وستوكناء الم تكن حياتكومماتك الشاهد الامين والصادق فجعلت",
        "sentence_x30": "تقدمه ذاتكخبز المسيح الطامر وخبز الاوطان والشرفاء اكرمن انطون يزبكالشيعيه",
        "sentence_x40": "لبنان والعالم الاسلامي الا بخطوه شيعيه جريئهوشجاعه تقول للوصي الفارسي",
        "sentence_x50": "كفي\n",
        "keywords": "اغتيال,رفيق,الحريري",
        "year": 2007,
        "label": "",
        "sentence_0": "اغتيال الرئيس الشميد رفيق الحريري خير معين وحاضنومساعد للطائفه الشيعيه",
        "sentence_10": "ويكفي نذكر المؤسساتا الليبي وكثير المواقف المشهوده بحيث كانت تعتبرشهودا",
        "sentence_20": "باعمالنا وكلامنا وستوكناء الم تكن حياتكومماتك الشاهد الامين والصادق فجعلت",
        "sentence_30": "تقدمه ذاتكخبز المسيح الطامر وخبز الاوطان والشرفاء اكرمن انطون يزبكالشيعيه",
        "sentence_40": "لبنان والعالم الاسلامي الا بخطوه شيعيه جريئهوشجاعه تقول للوصي الفارسي",
        "sentence_50": "كفي\n"
    },
    "39": {
        "sentence_x0": "قتله رئيسالوزراء رفيق الحريري والئنابباسل فليحان ومرتكبي جميعالجرائم الارهابيه المرتبطه",
        "sentence_x10": "بهاءبدءا بمحاوله اغتيال النائب\n",
        "keywords": "اغتيال,رفيق,الحريري",
        "year": 2007,
        "label": "",
        "sentence_0": "قتله رئيسالوزراء رفيق الحريري والئنابباسل فليحان ومرتكبي جميعالجرائم الارهابيه المرتبطه",
        "sentence_10": "بهاءبدءا بمحاوله اغتيال النائب\n"
    },
    "40": {
        "sentence_x0": "ان الاوساط تعتبر انهحان الوقت تتخذ السلطاتالسوريه الاجراءاتحق المسؤولين الامتيينالسوريين",
        "sentence_x10": "عملوا لبنانخلال الوجود السوريوسوريا تخشي شكتتم محاكمه مسؤولين سابقينشاركوا اغتيال",
        "sentence_x20": "الرئيس رفيقالحريري المحكمه الطابعالدولي وهي تحاول جاهمدهحلفائها الساحه اللبنانيهتعديل قانون",
        "sentence_x30": "المحكمه\n",
        "keywords": "اغتيال,رفيق,الحريري",
        "year": 2007,
        "label": "",
        "sentence_0": "ان الاوساط تعتبر انهحان الوقت تتخذ السلطاتالسوريه الاجراءاتحق المسؤولين الامتيينالسوريين",
        "sentence_10": "عملوا لبنانخلال الوجود السوريوسوريا تخشي شكتتم محاكمه مسؤولين سابقينشاركوا اغتيال",
        "sentence_20": "الرئيس رفيقالحريري المحكمه الطابعالدولي وهي تحاول جاهمدهحلفائها الساحه اللبنانيهتعديل قانون",
        "sentence_30": "المحكمه\n"
    },
    "41": {
        "sentence_x0": "فعلي رغم توجه المتعاملينالتوظيفات القصيره الاجل عموماء يستدل عبر ازدياد",
        "sentence_x10": "الاكتتاباتسندات الخزينه فئتي الثلاثه اشهر والسته اشهر اغتيالالرئيس رفيق الحريري\n",
        "keywords": "اغتيال,رفيق,الحريري",
        "year": 2007,
        "label": "",
        "sentence_0": "فعلي رغم توجه المتعاملينالتوظيفات القصيره الاجل عموماء يستدل عبر ازدياد",
        "sentence_10": "الاكتتاباتسندات الخزينه فئتي الثلاثه اشهر والسته اشهر اغتيالالرئيس رفيق الحريري\n"
    },
    "42": {
        "sentence_x0": "والتقي الرئيس بوش والوزيرهرايس والنائب الحريري ضرورهالتعجيل عمل المحكمه الخاصهاقرتها",
        "sentence_x10": "الامم المتحده لمحاكمهالمتهمين باغتيال الرئيس رفيقالحريري ورفاقه الي الشخصياتالسياسيه والاعلاميه",
        "sentence_x20": "اغتيلتخلال انلسنتين الاخيرتين\n",
        "keywords": "اغتيال,رفيق,الحريري",
        "year": 2007,
        "label": "",
        "sentence_0": "والتقي الرئيس بوش والوزيرهرايس والنائب الحريري ضرورهالتعجيل عمل المحكمه الخاصهاقرتها",
        "sentence_10": "الامم المتحده لمحاكمهالمتهمين باغتيال الرئيس رفيقالحريري ورفاقه الي الشخصياتالسياسيه والاعلاميه",
        "sentence_20": "اغتيلتخلال انلسنتين الاخيرتين\n"
    },
    "43": {
        "sentence_x0": "تبقي موخدينالي ابد الابديندفاعا لبنانالعظيمجبران توينيعمال وامنيون ينصبون خيمه مكان",
        "sentence_x10": "انفجار الحافلتين عين علق امسلحسن عسلرايس نشجع جميع الاطراف لبنانحل",
        "sentence_x20": "خلافاتهم بالوسائل السلميهاكدت وزيره الخارجيه الاميركيه كوندوليزا ريسبيان اصدرته باسمها",
        "sentence_x30": "الذكري الثائيه لاغتيالالرئيس رفيق الحريريء ااستمرار التزام الولاياتالمتحده اقامه المحكمه",
        "sentence_x40": "الخاصه لجلب المسؤوليناغتيال رئيس الوزراء السابق الحريري وغيرهالوطنيين ضحوا بحياتهمم",
        "sentence_x50": "سبيل لبتان حروديموقراطي امام العداله صن\n",
        "keywords": "اغتيال,رفيق,الحريري",
        "year": 2007,
        "label": "",
        "sentence_0": "تبقي موخدينالي ابد الابديندفاعا لبنانالعظيمجبران توينيعمال وامنيون ينصبون خيمه مكان",
        "sentence_10": "انفجار الحافلتين عين علق امسلحسن عسلرايس نشجع جميع الاطراف لبنانحل",
        "sentence_20": "خلافاتهم بالوسائل السلميهاكدت وزيره الخارجيه الاميركيه كوندوليزا ريسبيان اصدرته باسمها",
        "sentence_30": "الذكري الثائيه لاغتيالالرئيس رفيق الحريريء ااستمرار التزام الولاياتالمتحده اقامه المحكمه",
        "sentence_40": "الخاصه لجلب المسؤوليناغتيال رئيس الوزراء السابق الحريري وغيرهالوطنيين ضحوا بحياتهمم",
        "sentence_50": "سبيل لبتان حروديموقراطي امام العداله صن\n"
    },
    "44": {
        "sentence_x0": "لجنه التحقيق الدوليه اغتيال واشار الي ان مولندا اقترحالرئيس رفيق",
        "sentence_x10": "الحريري والاغتيالات ان تستضيف المحكمه اعتذرتالسياسيه الاخري\n",
        "keywords": "اغتيال,رفيق,الحريري",
        "year": 2007,
        "label": "",
        "sentence_0": "لجنه التحقيق الدوليه اغتيال واشار الي ان مولندا اقترحالرئيس رفيق",
        "sentence_10": "الحريري والاغتيالات ان تستضيف المحكمه اعتذرتالسياسيه الاخري\n"
    },
    "45": {
        "sentence_x0": "وقد حظي المدير العام للامن العام السابق اللواء جميلالسيد بالقسم",
        "sentence_x10": "الاكبر الكتاب نصفه لانه جري مرحله تاريخيهمفصليه وضع البلاد اغتيال",
        "sentence_x20": "الرئيس رفيق الحريري والتداعياتالسياسيه والامنيه رافقته فكان دوره خاميا”\n",
        "keywords": "اغتيال,رفيق,الحريري",
        "year": 2007,
        "label": "",
        "sentence_0": "وقد حظي المدير العام للامن العام السابق اللواء جميلالسيد بالقسم",
        "sentence_10": "الاكبر الكتاب نصفه لانه جري مرحله تاريخيهمفصليه وضع البلاد اغتيال",
        "sentence_20": "الرئيس رفيق الحريري والتداعياتالسياسيه والامنيه رافقته فكان دوره خاميا”\n"
    },
    "46": {
        "sentence_x0": "الايجاز وعدم تجاوز المقال نفد عمليه اغتيال الرئيس رفيق الحريري\n",
        "keywords": "اغتيال,رفيق,الحريري",
        "year": 2007,
        "label": "",
        "sentence_0": "الايجاز وعدم تجاوز المقال نفد عمليه اغتيال الرئيس رفيق الحريري\n"
    },
    "47": {
        "sentence_x0": "وعلي سبيل المثال فالعمليه الارهابيه اغتيال الرئيسرفيق الحريري ومحاولات الاغتيال",
        "sentence_x10": "والاغتيالات سبقتوتلت معرضه للتسخيف خلال خطاب قانوني ومماطله\n",
        "keywords": "اغتيال,رفيق,الحريري",
        "year": 2007,
        "label": "",
        "sentence_0": "وعلي سبيل المثال فالعمليه الارهابيه اغتيال الرئيسرفيق الحريري ومحاولات الاغتيال",
        "sentence_10": "والاغتيالات سبقتوتلت معرضه للتسخيف خلال خطاب قانوني ومماطله\n"
    },
    "48": {
        "sentence_x0": "كمااكدموقف باريس المحكمه الدوليهالموكل اليها محاكمه المسؤوليناغتيال الرئيس رفيق الحريريقائلا",
        "sentence_x10": "المحكمه الدوليه'مزحه وفرنسا مستعده لدفع الاموالاللازمه لانشائما\n",
        "keywords": "اغتيال,رفيق,الحريري",
        "year": 2007,
        "label": "",
        "sentence_0": "كمااكدموقف باريس المحكمه الدوليهالموكل اليها محاكمه المسؤوليناغتيال الرئيس رفيق الحريريقائلا",
        "sentence_10": "المحكمه الدوليه'مزحه وفرنسا مستعده لدفع الاموالاللازمه لانشائما\n"
    },
    "49": {
        "sentence_x0": "افاباعلنت السلطات البلديه لايدشندام فوربرغ ضاحيه لامايالجمعه ان المحكمه الدوليه",
        "sentence_x10": "لمقاضاه المتممين باغتيال رئيس الوزراءاللبناني السابق رفيق الحريري ستتخذ مقرا",
        "sentence_x20": "المركز السابق لاجمزهالاستخبارات المولنديه المنطقه\n",
        "keywords": "اغتيال,رفيق,الحريري",
        "year": 2007,
        "label": "",
        "sentence_0": "افاباعلنت السلطات البلديه لايدشندام فوربرغ ضاحيه لامايالجمعه ان المحكمه الدوليه",
        "sentence_10": "لمقاضاه المتممين باغتيال رئيس الوزراءاللبناني السابق رفيق الحريري ستتخذ مقرا",
        "sentence_20": "المركز السابق لاجمزهالاستخبارات المولنديه المنطقه\n"
    }
}