{
    "0": {
        "sentence_x0": "وجاء الانسحاب اثر موجهاحتجاج شعبيه ضد اغتيال رئيس الوزراءالاسبق رفيق",
        "sentence_x10": "الحريري شباط\n",
        "keywords": "اغتيال,رفيق,الحريري",
        "year": 2009,
        "label": "",
        "sentence_0": "وجاء الانسحاب اثر موجهاحتجاج شعبيه ضد اغتيال رئيس الوزراءالاسبق رفيق",
        "sentence_10": "الحريري شباط\n"
    },
    "1": {
        "sentence_x0": "ويصادف السبتالذكري السنويه الرابعه لاغتيالالرئيس الشميد رفيق الحريريوقد اصدر رئيس",
        "sentence_x10": "مجلس الوزراهمذكره اداريه قت بللتعطيلناك دعوه الي احتقال بهذهالذكري\n",
        "keywords": "اغتيال,رفيق,الحريري",
        "year": 2009,
        "label": "",
        "sentence_0": "ويصادف السبتالذكري السنويه الرابعه لاغتيالالرئيس الشميد رفيق الحريريوقد اصدر رئيس",
        "sentence_10": "مجلس الوزراهمذكره اداريه قت بللتعطيلناك دعوه الي احتقال بهذهالذكري\n"
    },
    "2": {
        "sentence_x0": "فرفض الطرح وجوبه بحمله شرسه ضد العماداحجد العبد منسق تنفيذيعون",
        "sentence_x10": "العام تاريخ اعلانكلمته الموجمه الي العسكريين واللد حدسواء اكد يتشد",
        "sentence_x20": "احسن العلاقات سورياواطيبهاء انطلاقا احترام سياده الدولتينتكون سوريا سوريا ولبتان",
        "sentence_x30": "لبتانالمرحله جاء اغتيال رئيس الوزراء اللبنانيرفيق الحريري فاتهمت سوريا بالاغتيال",
        "sentence_x40": "وشنتحمله شرسه عليماء فكان الحدث بازمته صاعقااللبتانيين فسرع خروج السوريين\n",
        "keywords": "اغتيال,رفيق,الحريري",
        "year": 2009,
        "label": "",
        "sentence_0": "فرفض الطرح وجوبه بحمله شرسه ضد العماداحجد العبد منسق تنفيذيعون",
        "sentence_10": "العام تاريخ اعلانكلمته الموجمه الي العسكريين واللد حدسواء اكد يتشد",
        "sentence_20": "احسن العلاقات سورياواطيبهاء انطلاقا احترام سياده الدولتينتكون سوريا سوريا ولبتان",
        "sentence_30": "لبتانالمرحله جاء اغتيال رئيس الوزراء اللبنانيرفيق الحريري فاتهمت سوريا بالاغتيال",
        "sentence_40": "وشنتحمله شرسه عليماء فكان الحدث بازمته صاعقااللبتانيين فسرع خروج السوريين\n"
    },
    "3": {
        "sentence_x0": "ملمحا الي تورط الاجمزه السوريه واللبنانيه اغتيالرفيق الحريري واخذ الرئيس",
        "sentence_x10": "بشار الاسد سلسله الاخطاءالمرتكبه التعامل الشؤون قبل رئيس جهازالمخابرات العسكريه",
        "sentence_x20": "السوريه لبنان رستم غزاله\n",
        "keywords": "اغتيال,رفيق,الحريري",
        "year": 2009,
        "label": "",
        "sentence_0": "ملمحا الي تورط الاجمزه السوريه واللبنانيه اغتيالرفيق الحريري واخذ الرئيس",
        "sentence_10": "بشار الاسد سلسله الاخطاءالمرتكبه التعامل الشؤون قبل رئيس جهازالمخابرات العسكريه",
        "sentence_20": "السوريه لبنان رستم غزاله\n"
    },
    "4": {
        "sentence_x0": "بلا رسمياشخاص بينهم الضباط الاربعهتحتجزهم لصلتهم باغتيالالرئيس رفيق الحريري\n",
        "keywords": "اغتيال,رفيق,الحريري",
        "year": 2009,
        "label": "",
        "sentence_0": "بلا رسمياشخاص بينهم الضباط الاربعهتحتجزهم لصلتهم باغتيالالرئيس رفيق الحريري\n"
    },
    "5": {
        "sentence_x0": "نشر قبل ايامجوزف صادر حول علاقتهاخيرا النبطيه عيئه القضاءاتجازات التحقيق",
        "sentence_x10": "الدولي جريمه اغتيال الرئيس رفيق الحريريويعترض حق الاجهزه الامنيه قاعده",
        "sentence_x20": "المعلومات المستفيدا عبقريه وزير الاتصالات\n",
        "keywords": "اغتيال,رفيق,الحريري",
        "year": 2009,
        "label": "",
        "sentence_0": "نشر قبل ايامجوزف صادر حول علاقتهاخيرا النبطيه عيئه القضاءاتجازات التحقيق",
        "sentence_10": "الدولي جريمه اغتيال الرئيس رفيق الحريريويعترض حق الاجهزه الامنيه قاعده",
        "sentence_20": "المعلومات المستفيدا عبقريه وزير الاتصالات\n"
    },
    "6": {
        "sentence_x0": "الملف القضائي المتعلق باغتيالالرئيس رفيق الحريري والموجودلمدي القضاء التبناني للجالتحقيق",
        "sentence_x10": "الدوليه وهل سيتم تقلالموقوشين الي لاماي فاجابالقاضي المهتم اوسيكون مشرفا",
        "sentence_x20": "المحكمهقبل المحاكمه مو يقر اذاكان يتعين نقل الموقوفين عدمنقلهمء احد",
        "sentence_x30": "يعرف اليوميجول خاطر القاضي\n",
        "keywords": "اغتيال,رفيق,الحريري",
        "year": 2009,
        "label": "",
        "sentence_0": "الملف القضائي المتعلق باغتيالالرئيس رفيق الحريري والموجودلمدي القضاء التبناني للجالتحقيق",
        "sentence_10": "الدوليه وهل سيتم تقلالموقوشين الي لاماي فاجابالقاضي المهتم اوسيكون مشرفا",
        "sentence_20": "المحكمهقبل المحاكمه مو يقر اذاكان يتعين نقل الموقوفين عدمنقلهمء احد",
        "sentence_30": "يعرف اليوميجول خاطر القاضي\n"
    },
    "7": {
        "sentence_x0": "قال وزير سابق اذا كانتالمحكمه الطابعالدولي تبدا عملها الااربع سنواتارتكاب",
        "sentence_x10": "جريمه اغتيالالرئيس رفيق الحريريورفاقدفكم سنه سيتطلبصدور الاحكام عنماالجريمهتدرس الاحزاب الاسيما",
        "sentence_x20": "حزب الطاشناقتسميه مرشحيهاللانتخابات النيابيهالمقبله وفق طبيعهالتحالفات ستعقدهاالاحزاب الاخري وقدتعيد النظر",
        "sentence_x30": "ترشيحنواب حاليين\n",
        "keywords": "اغتيال,رفيق,الحريري",
        "year": 2009,
        "label": "",
        "sentence_0": "قال وزير سابق اذا كانتالمحكمه الطابعالدولي تبدا عملها الااربع سنواتارتكاب",
        "sentence_10": "جريمه اغتيالالرئيس رفيق الحريريورفاقدفكم سنه سيتطلبصدور الاحكام عنماالجريمهتدرس الاحزاب الاسيما",
        "sentence_20": "حزب الطاشناقتسميه مرشحيهاللانتخابات النيابيهالمقبله وفق طبيعهالتحالفات ستعقدهاالاحزاب الاخري وقدتعيد النظر",
        "sentence_30": "ترشيحنواب حاليين\n"
    },
    "8": {
        "sentence_x0": "انظر الماده النظامجواب السلطات القضائيه اللبناني الامر بتنازل للسلطه القضائيه",
        "sentence_x10": "الليتانيهالمعنيه بقضيه المجوم الارهابي ضد رئيس الوزراء رفيق الحريري واخرين",
        "sentence_x20": "اختصامهاءللمحكمه الخاصه للبنان المؤرخ اذار مارس نيسان ابريل المشاراليه ياتي",
        "sentence_x30": "بغباره جواب السلطات اللبنانيه المؤرخ نيسان ابويلائمه باسماء جميع الااشخاص",
        "sentence_x40": "الموفوفين اطار قضيه اغتيال رئيس مجلس الوزراءاللبنائي السابق رفيق الحريري",
        "sentence_x50": "واخرين” المشار اليما ماياتي باسم القائمه\n",
        "keywords": "اغتيال,رفيق,الحريري",
        "year": 2009,
        "label": "",
        "sentence_0": "انظر الماده النظامجواب السلطات القضائيه اللبناني الامر بتنازل للسلطه القضائيه",
        "sentence_10": "الليتانيهالمعنيه بقضيه المجوم الارهابي ضد رئيس الوزراء رفيق الحريري واخرين",
        "sentence_20": "اختصامهاءللمحكمه الخاصه للبنان المؤرخ اذار مارس نيسان ابريل المشاراليه ياتي",
        "sentence_30": "بغباره جواب السلطات اللبنانيه المؤرخ نيسان ابويلائمه باسماء جميع الااشخاص",
        "sentence_40": "الموفوفين اطار قضيه اغتيال رئيس مجلس الوزراءاللبنائي السابق رفيق الحريري",
        "sentence_50": "واخرين” المشار اليما ماياتي باسم القائمه\n"
    },
    "9": {
        "sentence_x0": "وتوقف المكتب الذكري الرابعه لاغتيال الرئيس رفيقالحريري ورفاقه وراي ان",
        "sentence_x10": "المناسبه يجب تكون وقفه للصلاه لجميعشهداء انتفاضه الاستقلال للذين سقطوا",
        "sentence_x20": "سبيل رفع الوصايهلبنان واستعاده سيلادته\n",
        "keywords": "اغتيال,رفيق,الحريري",
        "year": 2009,
        "label": "",
        "sentence_0": "وتوقف المكتب الذكري الرابعه لاغتيال الرئيس رفيقالحريري ورفاقه وراي ان",
        "sentence_10": "المناسبه يجب تكون وقفه للصلاه لجميعشهداء انتفاضه الاستقلال للذين سقطوا",
        "sentence_20": "سبيل رفع الوصايهلبنان واستعاده سيلادته\n"
    },
    "10": {
        "sentence_x0": "نيويورك كالاتي الجنيه نالضباط الاربعه ملف اغتيال الرئيس رفيق قيمتها",
        "sentence_x10": "دولاراء مقابل تداول للاورو شي مقايل اول الاسجراء الريال دولار",
        "sentence_x20": "الروبيه لرويل لين الكورون الكورون الكورون اليولرور اول استرليني البرا",
        "sentence_x30": "المنديه اقيا الكنديالحريري الي خلاف المحكمه الدوا صكا بقيمه دولارا",
        "sentence_x40": "امس نشي كوخ الروسي اليلبائيا الاسوجي الماتارك المرعيخاصه بلبخان دوعو\n",
        "keywords": "اغتيال,رفيق,الحريري",
        "year": 2009,
        "label": "",
        "sentence_0": "نيويورك كالاتي الجنيه نالضباط الاربعه ملف اغتيال الرئيس رفيق قيمتها",
        "sentence_10": "دولاراء مقابل تداول للاورو شي مقايل اول الاسجراء الريال دولار",
        "sentence_20": "الروبيه لرويل لين الكورون الكورون الكورون اليولرور اول استرليني البرا",
        "sentence_30": "المنديه اقيا الكنديالحريري الي خلاف المحكمه الدوا صكا بقيمه دولارا",
        "sentence_40": "امس نشي كوخ الروسي اليلبائيا الاسوجي الماتارك المرعيخاصه بلبخان دوعو\n"
    },
    "11": {
        "sentence_x0": "عباره اخذ العلم بانطلاقه المحكمه الخاصهستحاكم المتورطين اغتيال الرئيس رفيق",
        "sentence_x10": "الحريري\n",
        "keywords": "اغتيال,رفيق,الحريري",
        "year": 2009,
        "label": "",
        "sentence_0": "عباره اخذ العلم بانطلاقه المحكمه الخاصهستحاكم المتورطين اغتيال الرئيس رفيق",
        "sentence_10": "الحريري\n"
    },
    "12": {
        "sentence_x0": "السؤال يتناول التوقيت اي وكيفءاذا كانت اداره اوباما ستعيد سفيرها",
        "sentence_x10": "الي سورياالقريب الفاجل بعدما سحبت سفيرتها دمشقاثر اغتيال الرئيس رفيق",
        "sentence_x20": "الحريري شباط\n",
        "keywords": "اغتيال,رفيق,الحريري",
        "year": 2009,
        "label": "",
        "sentence_0": "السؤال يتناول التوقيت اي وكيفءاذا كانت اداره اوباما ستعيد سفيرها",
        "sentence_10": "الي سورياالقريب الفاجل بعدما سحبت سفيرتها دمشقاثر اغتيال الرئيس رفيق",
        "sentence_20": "الحريري شباط\n"
    },
    "13": {
        "sentence_x0": "وفي موضوع الضباط الاربعهالموقوفين لبنان قال فنسنتوضع مؤلاء الضباط سيكونرهن",
        "sentence_x10": "مشاورات المدعي العاموالسلطات اللبناتيه وقرار ارسللهممتامتروك للسلطاتواكد انه الاناتجام موجه",
        "sentence_x20": "الي شخصربط مساله فتح الباب امامالنظر الاغتيالات الاخريبالاضافه الي اغتيال",
        "sentence_x30": "الرئيس رفيقالحريري\n",
        "keywords": "اغتيال,رفيق,الحريري",
        "year": 2009,
        "label": "",
        "sentence_0": "وفي موضوع الضباط الاربعهالموقوفين لبنان قال فنسنتوضع مؤلاء الضباط سيكونرهن",
        "sentence_10": "مشاورات المدعي العاموالسلطات اللبناتيه وقرار ارسللهممتامتروك للسلطاتواكد انه الاناتجام موجه",
        "sentence_20": "الي شخصربط مساله فتح الباب امامالنظر الاغتيالات الاخريبالاضافه الي اغتيال",
        "sentence_30": "الرئيس رفيقالحريري\n"
    },
    "14": {
        "sentence_x0": "ودعا اللبتانيين الحريريء مجرد استعادهاما والطائفه الارمنيه شامر الغضب والالم",
        "sentence_x10": "لهذه الجريمها الي للمشاركه احياء الارهابيه التكراء واتماالذكري الرابعه لاغتيال",
        "sentence_x20": "الرئيس ايضا الي تاكيد التزامنا القويرفيق الحريري شباطء ومعرفه اغتال",
        "sentence_x30": "شهداءهم الابرار اتجاح مشروع الدوله وجهوعن التعرض لاحد اعضاء وعلي",
        "sentence_x40": "راسهم الرئيس الحريري”\n",
        "keywords": "اغتيال,رفيق,الحريري",
        "year": 2009,
        "label": "",
        "sentence_0": "ودعا اللبتانيين الحريريء مجرد استعادهاما والطائفه الارمنيه شامر الغضب والالم",
        "sentence_10": "لهذه الجريمها الي للمشاركه احياء الارهابيه التكراء واتماالذكري الرابعه لاغتيال",
        "sentence_20": "الرئيس ايضا الي تاكيد التزامنا القويرفيق الحريري شباطء ومعرفه اغتال",
        "sentence_30": "شهداءهم الابرار اتجاح مشروع الدوله وجهوعن التعرض لاحد اعضاء وعلي",
        "sentence_40": "راسهم الرئيس الحريري”\n"
    },
    "15": {
        "sentence_x0": "وضع اكليلا تكريميا ضريح الحريريامل السفير الروسي سيرفيبوكين ان يكون",
        "sentence_x10": "نشاطالمحكمه الدوليه الخاصه بافتيالالرئيس رفيق الخريري مسيسوغير متحازء لتصبح فاعله",
        "sentence_x20": "وتؤديالي الكشف حقيقه مذاالاغتيال البشع والمستتكرالروس\n",
        "keywords": "اغتيال,رفيق,الحريري",
        "year": 2009,
        "label": "",
        "sentence_0": "وضع اكليلا تكريميا ضريح الحريريامل السفير الروسي سيرفيبوكين ان يكون",
        "sentence_10": "نشاطالمحكمه الدوليه الخاصه بافتيالالرئيس رفيق الخريري مسيسوغير متحازء لتصبح فاعله",
        "sentence_20": "وتؤديالي الكشف حقيقه مذاالاغتيال البشع والمستتكرالروس\n"
    },
    "16": {
        "sentence_x0": "الذكري الرابعه لاغتيال الرئيسرفيق الحريري والحديث احتمالترشح السنيوره الوزيره الحريريالمقعدين",
        "sentence_x10": "السنيين صيداءوقبل ثلاثه اشمر الانتخاباتب نبيه بري وترافقتليلا توزيع بيانات",
        "sentence_x20": "قري جنوبيهتنتقد زياره رئيس الحكومهتحت عنوان رجل الوفاء بامتيازابن صيدا",
        "sentence_x30": "البار رئيس مجلس الوزراءفؤاد السنيوره كرمت الشبكهالمدرسيه لصيدا والجوار باشرافالوزيره",
        "sentence_x40": "الحريري الرئيس السنيورهاحتخال اقيم قاعه ثاتويهرفيق الحريري لمناسبه الذكري الرابعه\n",
        "keywords": "اغتيال,رفيق,الحريري",
        "year": 2009,
        "label": "",
        "sentence_0": "الذكري الرابعه لاغتيال الرئيسرفيق الحريري والحديث احتمالترشح السنيوره الوزيره الحريريالمقعدين",
        "sentence_10": "السنيين صيداءوقبل ثلاثه اشمر الانتخاباتب نبيه بري وترافقتليلا توزيع بيانات",
        "sentence_20": "قري جنوبيهتنتقد زياره رئيس الحكومهتحت عنوان رجل الوفاء بامتيازابن صيدا",
        "sentence_30": "البار رئيس مجلس الوزراءفؤاد السنيوره كرمت الشبكهالمدرسيه لصيدا والجوار باشرافالوزيره",
        "sentence_40": "الحريري الرئيس السنيورهاحتخال اقيم قاعه ثاتويهرفيق الحريري لمناسبه الذكري الرابعه\n"
    },
    "17": {
        "sentence_x0": "جنبلاطء وجل الافضلاليوم التحالف القوي الطوائف الاخري غابت خلال سنه",
        "sentence_x10": "بعناوين السياده والاستقلال ان مخاوف حقيقيه النوع الشائعات حول جنبلاط",
        "sentence_x20": "وهلالسئه والدروز الي حد اذي الي استبعاد ابرز تحققا خروج",
        "sentence_x30": "سوريا لبنان نيسان يمكن ان يطول مقام الرئاسه حال قوز",
        "sentence_x40": "القوي المسيحيه عقده قبل الانتخابات اوا الشخصيات القوي كان دور",
        "sentence_x50": "كبير وفاعل اثر اغتيال الرئيس رفيق الحريري\n",
        "keywords": "اغتيال,رفيق,الحريري",
        "year": 2009,
        "label": "",
        "sentence_0": "جنبلاطء وجل الافضلاليوم التحالف القوي الطوائف الاخري غابت خلال سنه",
        "sentence_10": "بعناوين السياده والاستقلال ان مخاوف حقيقيه النوع الشائعات حول جنبلاط",
        "sentence_20": "وهلالسئه والدروز الي حد اذي الي استبعاد ابرز تحققا خروج",
        "sentence_30": "سوريا لبنان نيسان يمكن ان يطول مقام الرئاسه حال قوز",
        "sentence_40": "القوي المسيحيه عقده قبل الانتخابات اوا الشخصيات القوي كان دور",
        "sentence_50": "كبير وفاعل اثر اغتيال الرئيس رفيق الحريري\n"
    },
    "18": {
        "sentence_x0": "اكد مسؤولون دوليونمعنيون مباشره بملف جريمهاغتيال الرئيس رفيق الحريري ورفاقه",
        "sentence_x10": "لجمات غربيهولوروبيه رسميه ان عمل المحكمه الخاصه اجللبتان مستمر الي",
        "sentence_x20": "النهايه لان لجنه التحقيق الدوليه\n",
        "keywords": "اغتيال,رفيق,الحريري",
        "year": 2009,
        "label": "",
        "sentence_0": "اكد مسؤولون دوليونمعنيون مباشره بملف جريمهاغتيال الرئيس رفيق الحريري ورفاقه",
        "sentence_10": "لجمات غربيهولوروبيه رسميه ان عمل المحكمه الخاصه اجللبتان مستمر الي",
        "sentence_20": "النهايه لان لجنه التحقيق الدوليه\n"
    },
    "19": {
        "sentence_x0": "التقي وفدا كبيرا نساء المستقبل”البقاع ومما قال افتالوا الرئيس الشهيد",
        "sentence_x10": "رفيقالحريري لانه كار مشروعا وطنيا متكاملاءوقد تجحوا الاغتيال الجسدي لكنهم",
        "sentence_x20": "فشلواالاغتيال السياسي لان مشروع الرئيس الشهيد يزالقائما وحيا مناءيحاولون عبثا",
        "sentence_x30": "اتهامنا بللفساد ولكتي فقول انالفساد متجذر فيهمء وانهم اصل الفسادء",
        "sentence_x40": "فقدافسدوا الارض والبلاد اتجزه الرئيس الحريريكان اجل اللبنانيين وليس لفئه",
        "sentence_x50": "منهم وليسلفئه بدون الاخري\n",
        "keywords": "اغتيال,رفيق,الحريري",
        "year": 2009,
        "label": "",
        "sentence_0": "التقي وفدا كبيرا نساء المستقبل”البقاع ومما قال افتالوا الرئيس الشهيد",
        "sentence_10": "رفيقالحريري لانه كار مشروعا وطنيا متكاملاءوقد تجحوا الاغتيال الجسدي لكنهم",
        "sentence_20": "فشلواالاغتيال السياسي لان مشروع الرئيس الشهيد يزالقائما وحيا مناءيحاولون عبثا",
        "sentence_30": "اتهامنا بللفساد ولكتي فقول انالفساد متجذر فيهمء وانهم اصل الفسادء",
        "sentence_40": "فقدافسدوا الارض والبلاد اتجزه الرئيس الحريريكان اجل اللبنانيين وليس لفئه",
        "sentence_50": "منهم وليسلفئه بدون الاخري\n"
    },
    "20": {
        "sentence_x0": "وبلمار المدعي العام للمحكمه الخاصهللبنان والامين العام الهم بنفسه عنوان",
        "sentence_x10": "نصرالله الاول يزالقبل اغتيال الرئيس رفيق الحريري وبعد اغتياله\n",
        "keywords": "اغتيال,رفيق,الحريري",
        "year": 2009,
        "label": "",
        "sentence_0": "وبلمار المدعي العام للمحكمه الخاصهللبنان والامين العام الهم بنفسه عنوان",
        "sentence_10": "نصرالله الاول يزالقبل اغتيال الرئيس رفيق الحريري وبعد اغتياله\n"
    },
    "21": {
        "sentence_x0": "ويضيف بري التواب مسؤولتقصير الحكومه وانا نواتزلم يحمل الامر فان",
        "sentence_x10": "الرئيس السنيوره يريدمانا المحكمه الدوليه الخاصه باغتيال الرئيسرفيق الحريري يرد",
        "sentence_x20": "رئيس المجلس المحكمه اصبحتديار لاماي لاحقاق الحق\n",
        "keywords": "اغتيال,رفيق,الحريري",
        "year": 2009,
        "label": "",
        "sentence_0": "ويضيف بري التواب مسؤولتقصير الحكومه وانا نواتزلم يحمل الامر فان",
        "sentence_10": "الرئيس السنيوره يريدمانا المحكمه الدوليه الخاصه باغتيال الرئيسرفيق الحريري يرد",
        "sentence_20": "رئيس المجلس المحكمه اصبحتديار لاماي لاحقاق الحق\n"
    },
    "22": {
        "sentence_x0": "انا اعلم اتكم المنطقهالدرزي المشايخ شريف ابو حمدان الله تحريف",
        "sentence_x10": "العداله استخدامها والتضامن جميع الفئات العزيزه بالذات وفي تياروسليمان غائم",
        "sentence_x20": "ونصوح حيدر لفير امنا وامنتم شيخ سعدء يحتضنها الشوف والاقليم",
        "sentence_x30": "المستقبل امتداد لبنان قبلوفؤاد البعيني ورئيس مؤسسه لفير مالوصي والدكم",
        "sentence_x40": "طول مؤكدا التمدئه للولوج اغتيال رفيق الحريري وبعد عنوان جتموزالعرفان",
        "sentence_x50": "التوحيديه الشيخ علي حياته وحتي استشهاده محبه الي الانتخابات وممارسه",
        "sentence_x60": "حقنا الاعتدال والاستقرار البلدء دبا\n",
        "keywords": "اغتيال,رفيق,الحريري",
        "year": 2009,
        "label": "",
        "sentence_0": "انا اعلم اتكم المنطقهالدرزي المشايخ شريف ابو حمدان الله تحريف",
        "sentence_10": "العداله استخدامها والتضامن جميع الفئات العزيزه بالذات وفي تياروسليمان غائم",
        "sentence_20": "ونصوح حيدر لفير امنا وامنتم شيخ سعدء يحتضنها الشوف والاقليم",
        "sentence_30": "المستقبل امتداد لبنان قبلوفؤاد البعيني ورئيس مؤسسه لفير مالوصي والدكم",
        "sentence_40": "طول مؤكدا التمدئه للولوج اغتيال رفيق الحريري وبعد عنوان جتموزالعرفان",
        "sentence_50": "التوحيديه الشيخ علي حياته وحتي استشهاده محبه الي الانتخابات وممارسه",
        "sentence_60": "حقنا الاعتدال والاستقرار البلدء دبا\n"
    },
    "23": {
        "sentence_x0": "ولعل ابداء مؤيدي سوريا واصدقاكها لبناناستعدادهم لاداء دور الوسيط جتبلاط",
        "sentence_x10": "ودمشق واحياناالحريري ودمشق يعزز الاعتقاد يكنالواضح ان الامور تنضج وبجهه",
        "sentence_x20": "والحريري وجنبلاطمكمن الخلاف شخصياء يتعلق بملفات كبيره بدءاالموقف المحكمه الدوليه",
        "sentence_x30": "اغتيال الرئيس رفيقالحريري وسائر شهداء الاغتيال السياسيء وصولا الي ترسيعالحدود",
        "sentence_x40": "ووقف التدخلات واققال المعسكرات المحسوبهسوريا خارج المخيمات الفلسطينيه\n",
        "keywords": "اغتيال,رفيق,الحريري",
        "year": 2009,
        "label": "",
        "sentence_0": "ولعل ابداء مؤيدي سوريا واصدقاكها لبناناستعدادهم لاداء دور الوسيط جتبلاط",
        "sentence_10": "ودمشق واحياناالحريري ودمشق يعزز الاعتقاد يكنالواضح ان الامور تنضج وبجهه",
        "sentence_20": "والحريري وجنبلاطمكمن الخلاف شخصياء يتعلق بملفات كبيره بدءاالموقف المحكمه الدوليه",
        "sentence_30": "اغتيال الرئيس رفيقالحريري وسائر شهداء الاغتيال السياسيء وصولا الي ترسيعالحدود",
        "sentence_40": "ووقف التدخلات واققال المعسكرات المحسوبهسوريا خارج المخيمات الفلسطينيه\n"
    },
    "24": {
        "sentence_x0": "المدعي ابو بكر حمود تقريب فتع الاسلامتنظيم القاعده خلال سفره",
        "sentence_x10": "الي للسعوديه قال المتهمانه تردد وقتذاك الشارع ان الاخير سافر",
        "sentence_x20": "والمدهينبيل رحيم الي السعوديه اجل المالوسئل اذا كان يشكل وتبيل",
        "sentence_x30": "رحيم وزمير عيسيمركز المسؤوليه مجلس الشوري تديهم فاجابنافيا ان يكون",
        "sentence_x40": "يشكلونه معمد دار الخليلاح تماع ضمهم والتركي والسنكريمع'فتح الاسلام” ورد",
        "sentence_x50": "افادتهوسئل ايضا اغتيال الرئيس رفيق الحريري وافقتتاليف مجموعه تهتم بامور",
        "sentence_x60": "المسلمين ومساعدهين وحددت وظيفه افرادهاءالتدريب السلاج وانت مسؤولها الشرعي فاجابكلام",
        "sentence_x70": "شرعي ولم اقله ابدا جميع افاداتي\n",
        "keywords": "اغتيال,رفيق,الحريري",
        "year": 2009,
        "label": "",
        "sentence_0": "المدعي ابو بكر حمود تقريب فتع الاسلامتنظيم القاعده خلال سفره",
        "sentence_10": "الي للسعوديه قال المتهمانه تردد وقتذاك الشارع ان الاخير سافر",
        "sentence_20": "والمدهينبيل رحيم الي السعوديه اجل المالوسئل اذا كان يشكل وتبيل",
        "sentence_30": "رحيم وزمير عيسيمركز المسؤوليه مجلس الشوري تديهم فاجابنافيا ان يكون",
        "sentence_40": "يشكلونه معمد دار الخليلاح تماع ضمهم والتركي والسنكريمع'فتح الاسلام” ورد",
        "sentence_50": "افادتهوسئل ايضا اغتيال الرئيس رفيق الحريري وافقتتاليف مجموعه تهتم بامور",
        "sentence_60": "المسلمين ومساعدهين وحددت وظيفه افرادهاءالتدريب السلاج وانت مسؤولها الشرعي فاجابكلام",
        "sentence_70": "شرعي ولم اقله ابدا جميع افاداتي\n"
    },
    "25": {
        "sentence_x0": "ومصالح الحكمسوريا ومواقفه تتفير حسب مصالحه الخاصه قبلاتفلقيه الطائف واثناء",
        "sentence_x10": "الحروب عاتاما لينانء وبعدالطائف اتاحت الوصايه لبنانء والتي تحولتالي هيمنه",
        "sentence_x20": "امتيه وتدخل مباشر شؤونه الداخليه بداتبمرونه واشتدت الي وصلت الي",
        "sentence_x30": "ذروتها التحولالوصليه الي هيمنه امتيه كامله وتدخل مباشر واعتقالاللبناتيه خاصه",
        "sentence_x40": "بمجيء عمد الرئيسوالحديث هذايطول ويتطلب دراسه تاريخيهفعلا تطرح التجربه اللبنانيه",
        "sentence_x50": "علاقتها المعقدهسوريا الشقيقه وخاصه المرحله الانتقاليه الشديدهالتعقيد اتفاقيه الطائف الي",
        "sentence_x60": "مجيء عمد لحودءالي نمايه اغتيال الرئيس رفيق الحريري\n",
        "keywords": "اغتيال,رفيق,الحريري",
        "year": 2009,
        "label": "",
        "sentence_0": "ومصالح الحكمسوريا ومواقفه تتفير حسب مصالحه الخاصه قبلاتفلقيه الطائف واثناء",
        "sentence_10": "الحروب عاتاما لينانء وبعدالطائف اتاحت الوصايه لبنانء والتي تحولتالي هيمنه",
        "sentence_20": "امتيه وتدخل مباشر شؤونه الداخليه بداتبمرونه واشتدت الي وصلت الي",
        "sentence_30": "ذروتها التحولالوصليه الي هيمنه امتيه كامله وتدخل مباشر واعتقالاللبناتيه خاصه",
        "sentence_40": "بمجيء عمد الرئيسوالحديث هذايطول ويتطلب دراسه تاريخيهفعلا تطرح التجربه اللبنانيه",
        "sentence_50": "علاقتها المعقدهسوريا الشقيقه وخاصه المرحله الانتقاليه الشديدهالتعقيد اتفاقيه الطائف الي",
        "sentence_60": "مجيء عمد لحودءالي نمايه اغتيال الرئيس رفيق الحريري\n"
    },
    "26": {
        "sentence_x0": "تقتضي الامانه الاخلاقيه يقر كاتب السطور بانهءوكثر رجال السياسه الاعلام",
        "sentence_x10": "اندقع اتهام الضباطالاربعه بالضلوع اغتيال الرئيس الشهيد رفيق الحريرياشتراكا او",
        "sentence_x20": "تحريضا او تسهيلا او تسترا اخقاء لمقالمالجريمه بناء قراءه سياسيه",
        "sentence_x30": "اسانيد قويه\n",
        "keywords": "اغتيال,رفيق,الحريري",
        "year": 2009,
        "label": "",
        "sentence_0": "تقتضي الامانه الاخلاقيه يقر كاتب السطور بانهءوكثر رجال السياسه الاعلام",
        "sentence_10": "اندقع اتهام الضباطالاربعه بالضلوع اغتيال الرئيس الشهيد رفيق الحريرياشتراكا او",
        "sentence_20": "تحريضا او تسهيلا او تسترا اخقاء لمقالمالجريمه بناء قراءه سياسيه",
        "sentence_30": "اسانيد قويه\n"
    },
    "27": {
        "sentence_x0": "المحامين ورجال القانون السوريين والاجانب لتوليمهمه الدفاع امام المحكمه الدوليه",
        "sentence_x10": "الخاصه بلبثانالمسؤولين السوريين يمكن يتجمهممدعي عام المحكمه بالتورط جريمه اغتيالالرئيس",
        "sentence_x20": "رفيق الحريري ورفاقه حال طلب القضاهتسليم الي العداله الدوليه لمحاكمتهممتهمين",
        "sentence_x30": "لبتانيين الجريمه\n",
        "keywords": "اغتيال,رفيق,الحريري",
        "year": 2009,
        "label": "",
        "sentence_0": "المحامين ورجال القانون السوريين والاجانب لتوليمهمه الدفاع امام المحكمه الدوليه",
        "sentence_10": "الخاصه بلبثانالمسؤولين السوريين يمكن يتجمهممدعي عام المحكمه بالتورط جريمه اغتيالالرئيس",
        "sentence_20": "رفيق الحريري ورفاقه حال طلب القضاهتسليم الي العداله الدوليه لمحاكمتهممتهمين",
        "sentence_30": "لبتانيين الجريمه\n"
    },
    "28": {
        "sentence_x0": "السعوديه وسوريا وهل تعتقد اناستمرار التوتر بيتهما سببه اغتيال الرئيس",
        "sentence_x10": "رفيقالحريريء او الامانه الشخصيه للعامل السعودياو العلاقه القويه جدا سوريا",
        "sentence_x20": "وايران سالت\n",
        "keywords": "اغتيال,رفيق,الحريري",
        "year": 2009,
        "label": "",
        "sentence_0": "السعوديه وسوريا وهل تعتقد اناستمرار التوتر بيتهما سببه اغتيال الرئيس",
        "sentence_10": "رفيقالحريريء او الامانه الشخصيه للعامل السعودياو العلاقه القويه جدا سوريا",
        "sentence_20": "وايران سالت\n"
    },
    "29": {
        "sentence_x0": "تعقد المحكمه الدوليه جريمه اغتيال الرئيس الشميد رفيقالحريري ورفاقه والجرائم",
        "sentence_x10": "المترابطه\n",
        "keywords": "اغتيال,رفيق,الحريري",
        "year": 2009,
        "label": "",
        "sentence_0": "تعقد المحكمه الدوليه جريمه اغتيال الرئيس الشميد رفيقالحريري ورفاقه والجرائم",
        "sentence_10": "المترابطه\n"
    },
    "30": {
        "sentence_x0": "اذ ابطلالمجلس الدستوري نيابه غبريال المر واعلن مخيبتائبا صوتاءبقيت ترددات",
        "sentence_x10": "المتن الفرعيه تتفاعل اليحصول انتخابات عاموظلت الانعكاسات السياسيه ترخي بثقلهاالساحه",
        "sentence_x20": "الحديث التمديد للرئيساميل لحود ابن المتن الي اغتيال الرئيسرفيق الحريري\n",
        "keywords": "اغتيال,رفيق,الحريري",
        "year": 2009,
        "label": "",
        "sentence_0": "اذ ابطلالمجلس الدستوري نيابه غبريال المر واعلن مخيبتائبا صوتاءبقيت ترددات",
        "sentence_10": "المتن الفرعيه تتفاعل اليحصول انتخابات عاموظلت الانعكاسات السياسيه ترخي بثقلهاالساحه",
        "sentence_20": "الحديث التمديد للرئيساميل لحود ابن المتن الي اغتيال الرئيسرفيق الحريري\n"
    },
    "31": {
        "sentence_x0": "المحكمه الدوليه الخلصه بلبنانقال الرئيس سليم الحص يضع حدا رادعا",
        "sentence_x10": "ونمائيا لموجهاما وقد اتطلقت المحكمه الدوليه الاجرام ومخططه استباحعملهاء فاتنا",
        "sentence_x20": "ككل البلاد والعباد حاله متماديهترجو ان توفق الي وضع اليد",
        "sentence_x30": "يشهدها بلد او العالمرالجناه ارتكبوا جريمه اغتيال بالطريقه تمت لبنان",
        "sentence_x40": "قتلالرئيس الشهيد رفيق الحريري قتلء وتصفيه تصفيه ءورفاقه\n",
        "keywords": "اغتيال,رفيق,الحريري",
        "year": 2009,
        "label": "",
        "sentence_0": "المحكمه الدوليه الخلصه بلبنانقال الرئيس سليم الحص يضع حدا رادعا",
        "sentence_10": "ونمائيا لموجهاما وقد اتطلقت المحكمه الدوليه الاجرام ومخططه استباحعملهاء فاتنا",
        "sentence_20": "ككل البلاد والعباد حاله متماديهترجو ان توفق الي وضع اليد",
        "sentence_30": "يشهدها بلد او العالمرالجناه ارتكبوا جريمه اغتيال بالطريقه تمت لبنان",
        "sentence_40": "قتلالرئيس الشهيد رفيق الحريري قتلء وتصفيه تصفيه ءورفاقه\n"
    },
    "32": {
        "sentence_x0": "كانت اعلان لبنان الكبير قلب الجنوب مثال للعيش ااغيبه جسديا",
        "sentence_x10": "الاغتيال المشؤوم الطوال والاتجازات العظام واصدار الدستور الاول عام المشترك",
        "sentence_x20": "والوحده الوطنيه بشري مستمره في خطهالكننا مستمرون مسيرته الرئيس الشهيد",
        "sentence_x30": "رفيق الحريري رق الجمهوريه الثانيه تاكيد للمويه اللبنانيه\n",
        "keywords": "اغتيال,رفيق,الحريري",
        "year": 2009,
        "label": "",
        "sentence_0": "كانت اعلان لبنان الكبير قلب الجنوب مثال للعيش ااغيبه جسديا",
        "sentence_10": "الاغتيال المشؤوم الطوال والاتجازات العظام واصدار الدستور الاول عام المشترك",
        "sentence_20": "والوحده الوطنيه بشري مستمره في خطهالكننا مستمرون مسيرته الرئيس الشهيد",
        "sentence_30": "رفيق الحريري رق الجمهوريه الثانيه تاكيد للمويه اللبنانيه\n"
    },
    "33": {
        "sentence_x0": "يفتقد لبنان مواقفه الوطنيه الحكيمهبقلم الدكتور فوزي زيدانكان الهدف اغتيال",
        "sentence_x10": "الرئيس الشهيد رفيق الحريري القضاءمشروعه باقامه دوله المؤسسات القويه والعادله",
        "sentence_x20": "الترابالوطني كاملا\n",
        "keywords": "اغتيال,رفيق,الحريري",
        "year": 2009,
        "label": "",
        "sentence_0": "يفتقد لبنان مواقفه الوطنيه الحكيمهبقلم الدكتور فوزي زيدانكان الهدف اغتيال",
        "sentence_10": "الرئيس الشهيد رفيق الحريري القضاءمشروعه باقامه دوله المؤسسات القويه والعادله",
        "sentence_20": "الترابالوطني كاملا\n"
    },
    "34": {
        "sentence_x0": "بورصه بيروت مشاعرالاطمئنان اعقبت عمليهالافراج الضباط الاربعه ملفاغتيال الرئيس رفيق",
        "sentence_x10": "الحريرييبدو اتها طويت الي حد ماء خلاقاللفط رافق استذكار احداثيار",
        "sentence_x20": "يريالبعض ذكري مشؤومه والبعض\n",
        "keywords": "اغتيال,رفيق,الحريري",
        "year": 2009,
        "label": "",
        "sentence_0": "بورصه بيروت مشاعرالاطمئنان اعقبت عمليهالافراج الضباط الاربعه ملفاغتيال الرئيس رفيق",
        "sentence_10": "الحريرييبدو اتها طويت الي حد ماء خلاقاللفط رافق استذكار احداثيار",
        "sentence_20": "يريالبعض ذكري مشؤومه والبعض\n"
    },
    "35": {
        "sentence_x0": "وخصوصا ملاحقه جرائمجريمه افتيال الرئيس الشهيد الاغتيالات السياسيه السابقهرفيق الحريري",
        "sentence_x10": "رافقها وتلاها المشموله بولايه المحكمه الخاصهجرائم سياسيه\n",
        "keywords": "اغتيال,رفيق,الحريري",
        "year": 2009,
        "label": "",
        "sentence_0": "وخصوصا ملاحقه جرائمجريمه افتيال الرئيس الشهيد الاغتيالات السياسيه السابقهرفيق الحريري",
        "sentence_10": "رافقها وتلاها المشموله بولايه المحكمه الخاصهجرائم سياسيه\n"
    },
    "36": {
        "sentence_x0": "وحيا الشيعهحزيران اصبحت باهميه اذارء فان مشروعنا وطني قالت توي",
        "sentence_x10": "يكون ايار جديد وهذا رهن وحريته وسيادته فوق اعتبارء مختلف",
        "sentence_x20": "قري منطقه جزينعندي معلوماتمجال اخر وصف دلول مقال صحيفه در",
        "sentence_x30": "شبيفل الالمانيه حولاتام حزب الله باغتيال الرئيس الشهيد رفيق الحريري",
        "sentence_x40": "باوقال كتب المجله كتب بيروت وانا عنديمعلومات وان شاء الله",
        "sentence_x50": "يتصل التحقيق واقولها\n",
        "keywords": "اغتيال,رفيق,الحريري",
        "year": 2009,
        "label": "",
        "sentence_0": "وحيا الشيعهحزيران اصبحت باهميه اذارء فان مشروعنا وطني قالت توي",
        "sentence_10": "يكون ايار جديد وهذا رهن وحريته وسيادته فوق اعتبارء مختلف",
        "sentence_20": "قري منطقه جزينعندي معلوماتمجال اخر وصف دلول مقال صحيفه در",
        "sentence_30": "شبيفل الالمانيه حولاتام حزب الله باغتيال الرئيس الشهيد رفيق الحريري",
        "sentence_40": "باوقال كتب المجله كتب بيروت وانا عنديمعلومات وان شاء الله",
        "sentence_50": "يتصل التحقيق واقولها\n"
    },
    "37": {
        "sentence_x0": "وسبقللجنه التحقيق الدوليه ان استمعت الي افادته بالصفه ذاتماخلال عملها",
        "sentence_x10": "بيروت وقبل انتقال التحقيق برمته ملفاغتيال الرئيس رفيق الحريري الي",
        "sentence_x20": "المحكمه الخاصه بلبنانواعلان انتهاء عمل الاجنه ءرسمي الخطوه بانما تاريخيه",
        "sentence_x30": "ونقل الرئيسحكومه كويتيه جديدهدونما تغييرات اساسيهاصدر امس امير الكويت الشيخ",
        "sentence_x40": "الصباح الحاكمه شان الحكومه\n",
        "keywords": "اغتيال,رفيق,الحريري",
        "year": 2009,
        "label": "",
        "sentence_0": "وسبقللجنه التحقيق الدوليه ان استمعت الي افادته بالصفه ذاتماخلال عملها",
        "sentence_10": "بيروت وقبل انتقال التحقيق برمته ملفاغتيال الرئيس رفيق الحريري الي",
        "sentence_20": "المحكمه الخاصه بلبنانواعلان انتهاء عمل الاجنه ءرسمي الخطوه بانما تاريخيه",
        "sentence_30": "ونقل الرئيسحكومه كويتيه جديدهدونما تغييرات اساسيهاصدر امس امير الكويت الشيخ",
        "sentence_40": "الصباح الحاكمه شان الحكومه\n"
    },
    "38": {
        "sentence_x0": "وقد تم بالفعل تشكيل اذ نا تطوير الرقابه وراء للتحديات",
        "sentence_x10": "والشتائم لانكم اكبرموقوفين قضيه اغتيال الرئيس رفيق الحريري وقال المرحله",
        "sentence_x20": "مشروعتا ال ميدل ايست جوزف صادر\n",
        "keywords": "اغتيال,رفيق,الحريري",
        "year": 2009,
        "label": "",
        "sentence_0": "وقد تم بالفعل تشكيل اذ نا تطوير الرقابه وراء للتحديات",
        "sentence_10": "والشتائم لانكم اكبرموقوفين قضيه اغتيال الرئيس رفيق الحريري وقال المرحله",
        "sentence_20": "مشروعتا ال ميدل ايست جوزف صادر\n"
    },
    "39": {
        "sentence_x0": "البعام يحملون الشموعتتواصل النشاطات التحضيريهللذكري السنويه الرابعه لاغتيالالرئيس رفيق الحريري",
        "sentence_x10": "الرابععشر شباط الجاري\n",
        "keywords": "اغتيال,رفيق,الحريري",
        "year": 2009,
        "label": "",
        "sentence_0": "البعام يحملون الشموعتتواصل النشاطات التحضيريهللذكري السنويه الرابعه لاغتيالالرئيس رفيق الحريري",
        "sentence_10": "الرابععشر شباط الجاري\n"
    },
    "40": {
        "sentence_x0": "ولا وتكذيب المقائق مناجلمتاصرين لقوي الثلمن اذار ختام تظاهره اذار",
        "sentence_x10": "لمناسبه ذكري الولايات المتحده الاميركيه او اذار معنا حول الامر",
        "sentence_x20": "وتفوض ويلحق الضرر بالمواطنين اعرف سيكون شكل نستطيع اعلان خلاصه",
        "sentence_x30": "لاننا لاغتيال الرئيس رفيق الحريري الموقف الاوروبي او الانتخابات رئيس",
        "sentence_x40": "الجمهوريه حل المساله جراء سياساتهم الكيديه فحرم الانتخابات ظل ماتشهده",
        "sentence_x50": "نكون نعلن خطه عمل فريق واحد\n",
        "keywords": "اغتيال,رفيق,الحريري",
        "year": 2009,
        "label": "",
        "sentence_0": "ولا وتكذيب المقائق مناجلمتاصرين لقوي الثلمن اذار ختام تظاهره اذار",
        "sentence_10": "لمناسبه ذكري الولايات المتحده الاميركيه او اذار معنا حول الامر",
        "sentence_20": "وتفوض ويلحق الضرر بالمواطنين اعرف سيكون شكل نستطيع اعلان خلاصه",
        "sentence_30": "لاننا لاغتيال الرئيس رفيق الحريري الموقف الاوروبي او الانتخابات رئيس",
        "sentence_40": "الجمهوريه حل المساله جراء سياساتهم الكيديه فحرم الانتخابات ظل ماتشهده",
        "sentence_50": "نكون نعلن خطه عمل فريق واحد\n"
    },
    "41": {
        "sentence_x0": "لا يمكناصحابه ووضع حد لموجه الاجرام اليومء وقد اصبحت قضيهوالمجرمين",
        "sentence_x10": "استباحوا افتيال الرئيس الحريري عهدهوخططوا عبر اغتيال القضاء الدولي لامايء",
        "sentence_x20": "تظلكوكبه قياداته وعلي راسهم مضفه للافواه السياسيه مادامالشهيد الكبير الرئيس",
        "sentence_x30": "رفيق القاضي بثمار فصل الامر بقولهالحريري\n",
        "keywords": "اغتيال,رفيق,الحريري",
        "year": 2009,
        "label": "",
        "sentence_0": "لا يمكناصحابه ووضع حد لموجه الاجرام اليومء وقد اصبحت قضيهوالمجرمين",
        "sentence_10": "استباحوا افتيال الرئيس الحريري عهدهوخططوا عبر اغتيال القضاء الدولي لامايء",
        "sentence_20": "تظلكوكبه قياداته وعلي راسهم مضفه للافواه السياسيه مادامالشهيد الكبير الرئيس",
        "sentence_30": "رفيق القاضي بثمار فصل الامر بقولهالحريري\n"
    },
    "42": {
        "sentence_x0": "ستحاكم المتهمين باغتيالالرئيس رفيق الحريري وكل شهدا انتفاضهالاستقلال” يدخل لبنان",
        "sentence_x10": "الاحد المقبل مرحلهجديده المستوي السياسي وريماالمستوي التاسيسي\n",
        "keywords": "اغتيال,رفيق,الحريري",
        "year": 2009,
        "label": "",
        "sentence_0": "ستحاكم المتهمين باغتيالالرئيس رفيق الحريري وكل شهدا انتفاضهالاستقلال” يدخل لبنان",
        "sentence_10": "الاحد المقبل مرحلهجديده المستوي السياسي وريماالمستوي التاسيسي\n"
    },
    "43": {
        "sentence_x0": "قال ديبلوماسي اميركي مطلعاستقلال مبنان انجاز كبيرتقبل اداره اوباما ان",
        "sentence_x10": "يستغل نظام الرئيسبشار الاسد حوار اميركي معه لمحاوله عقد صفقهالولايات",
        "sentence_x20": "المتحده حساب تبنان المستقلحساب المحكمه الدوليه المكلفه النظرجريمه اغتيال الرئيس",
        "sentence_x30": "رفيق الحريري ورشاقه وفيجرائم سياسيه اخري\n",
        "keywords": "اغتيال,رفيق,الحريري",
        "year": 2009,
        "label": "",
        "sentence_0": "قال ديبلوماسي اميركي مطلعاستقلال مبنان انجاز كبيرتقبل اداره اوباما ان",
        "sentence_10": "يستغل نظام الرئيسبشار الاسد حوار اميركي معه لمحاوله عقد صفقهالولايات",
        "sentence_20": "المتحده حساب تبنان المستقلحساب المحكمه الدوليه المكلفه النظرجريمه اغتيال الرئيس",
        "sentence_30": "رفيق الحريري ورشاقه وفيجرائم سياسيه اخري\n"
    },
    "44": {
        "sentence_x0": "توقيف مطلوباتمكنت قطعات قوي الامنالداخلي توقيف مطلوباللقضاء بموجب مذكرات واحكامعدليه",
        "sentence_x10": "مختلفه الاراضيامس واول امسء اطارمهماتهافي مجال حفظ الامنوالنظام ومكافحه الجريمه",
        "sentence_x20": "بمختلفالفلثاء نيسانالقضاء تبلغ طلب قاضي الاجراءاتالتنازل اختصاصه ملف الحريريعلمت النهار",
        "sentence_x30": "ان القضاء اللبناتي تبلغ طلب قاضي الاجراءات التمهيديهالمحكمه الخاصه بلبنان",
        "sentence_x40": "دانيال فراتسين الرامي الي تنازل السلطاتالقضائيه اللبنانيه تحقق ملف جريمه",
        "sentence_x50": "اغتيال الرئيس رفيقالحريري ورفاقه اختصاصها لمصلحه المحكمه الدوليه\n",
        "keywords": "اغتيال,رفيق,الحريري",
        "year": 2009,
        "label": "",
        "sentence_0": "توقيف مطلوباتمكنت قطعات قوي الامنالداخلي توقيف مطلوباللقضاء بموجب مذكرات واحكامعدليه",
        "sentence_10": "مختلفه الاراضيامس واول امسء اطارمهماتهافي مجال حفظ الامنوالنظام ومكافحه الجريمه",
        "sentence_20": "بمختلفالفلثاء نيسانالقضاء تبلغ طلب قاضي الاجراءاتالتنازل اختصاصه ملف الحريريعلمت النهار",
        "sentence_30": "ان القضاء اللبناتي تبلغ طلب قاضي الاجراءات التمهيديهالمحكمه الخاصه بلبنان",
        "sentence_40": "دانيال فراتسين الرامي الي تنازل السلطاتالقضائيه اللبنانيه تحقق ملف جريمه",
        "sentence_50": "اغتيال الرئيس رفيقالحريري ورفاقه اختصاصها لمصلحه المحكمه الدوليه\n"
    },
    "45": {
        "sentence_x0": "وفد اللجنه شرح للوزيره الحريريان وعدم تركهم لان واجبهاللمتعاقدين الحق",
        "sentence_x10": "الدخول كونهم يدفعون حقوقمااسح اج غرائب وينزين وتلفون وكهرباءمشروع اول",
        "sentence_x20": "للتواصل التلامذه يعفم قريبابريد االكتروني لكل تلميذ واستاذاطلقته الحري يري",
        "sentence_x30": "صيداصيدا الذهار”الذكري الرابعه لاغتيال الرئيس رفيق الحريري\n",
        "keywords": "اغتيال,رفيق,الحريري",
        "year": 2009,
        "label": "",
        "sentence_0": "وفد اللجنه شرح للوزيره الحريريان وعدم تركهم لان واجبهاللمتعاقدين الحق",
        "sentence_10": "الدخول كونهم يدفعون حقوقمااسح اج غرائب وينزين وتلفون وكهرباءمشروع اول",
        "sentence_20": "للتواصل التلامذه يعفم قريبابريد االكتروني لكل تلميذ واستاذاطلقته الحري يري",
        "sentence_30": "صيداصيدا الذهار”الذكري الرابعه لاغتيال الرئيس رفيق الحريري\n"
    },
    "46": {
        "sentence_x0": "اذا كان اكتشافالمحرضين والمتفذين سيوقف مسلسل الاغتيالاتالمحقق بلمار اتخذ قراره",
        "sentence_x10": "مضي لكثر ثلاث سنواتشهدت تشاطات المحققين السابقين مثل بيتر فيتزجيرالدميليس",
        "sentence_x20": "وسيرع براميرتس وكان القضله الاربعهحسيما ذكر بلمار كلمت الشعب البنائياعمليه",
        "sentence_x30": "اغتيال الرئيس رفيق الحريري ورفاقهاضافه الي اعتداء ارتكبت لبتان\n",
        "keywords": "اغتيال,رفيق,الحريري",
        "year": 2009,
        "label": "",
        "sentence_0": "اذا كان اكتشافالمحرضين والمتفذين سيوقف مسلسل الاغتيالاتالمحقق بلمار اتخذ قراره",
        "sentence_10": "مضي لكثر ثلاث سنواتشهدت تشاطات المحققين السابقين مثل بيتر فيتزجيرالدميليس",
        "sentence_20": "وسيرع براميرتس وكان القضله الاربعهحسيما ذكر بلمار كلمت الشعب البنائياعمليه",
        "sentence_30": "اغتيال الرئيس رفيق الحريري ورفاقهاضافه الي اعتداء ارتكبت لبتان\n"
    },
    "47": {
        "sentence_x0": "وكان عرض للاستعداداتالجاريه للمشاركه احياءذكري شباط ءكباره وفتوح يدعوان اوسع",
        "sentence_x10": "مشاركه شباطراي النائب محمد كباره ان ذكري بدخول ال الدوليه",
        "sentence_x20": "حقباغتيال الرئيس رفيق الحريري العمل الفعلي الاول اذارشباط تكتسب السنه",
        "sentence_x30": "المقبل لايقاع القصاص بالجنااهميه خاصه تحفز المشاركه خططواومولوا وتفذواالواسعه فيهافي",
        "sentence_x40": "ساحه الحريه الجرائم استهدفت قياداتناوسط بيروت\n",
        "keywords": "اغتيال,رفيق,الحريري",
        "year": 2009,
        "label": "",
        "sentence_0": "وكان عرض للاستعداداتالجاريه للمشاركه احياءذكري شباط ءكباره وفتوح يدعوان اوسع",
        "sentence_10": "مشاركه شباطراي النائب محمد كباره ان ذكري بدخول ال الدوليه",
        "sentence_20": "حقباغتيال الرئيس رفيق الحريري العمل الفعلي الاول اذارشباط تكتسب السنه",
        "sentence_30": "المقبل لايقاع القصاص بالجنااهميه خاصه تحفز المشاركه خططواومولوا وتفذواالواسعه فيهافي",
        "sentence_40": "ساحه الحريه الجرائم استهدفت قياداتناوسط بيروت\n"
    },
    "48": {
        "sentence_x0": "وعندما ايدت بكركي قيام محكمه طابعدولي لمعرفه المقيقه اغتيال الرئيس",
        "sentence_x10": "رفيقالحريري ورشاقه اعتبر يريدون قيامهاءليظل المجرمون يسرحون ويمرحون بكركيوعندما ايدت",
        "sentence_x20": "بكركي قيام الحكومه بتصريفالاعمال ريثمايتم انتخاب رئيس للجمهوريه لاتهيجوز تعطيل",
        "sentence_x30": "مصالح الناس اعتبر البعض انبكركي تؤيد بقاء الحكومه البعضيريد تعطيل",
        "sentence_x40": "شيء لبنان حدهوعندما قال سيد يكركي ان الاكثريهاذا انتقلت الي",
        "sentence_x50": "قوي اذار اخطاراواخطاء سيكون وزنها التاريخي مصيرالوطن اعتبر البعض انه",
        "sentence_x60": "يقف قوياذار\n",
        "keywords": "اغتيال,رفيق,الحريري",
        "year": 2009,
        "label": "",
        "sentence_0": "وعندما ايدت بكركي قيام محكمه طابعدولي لمعرفه المقيقه اغتيال الرئيس",
        "sentence_10": "رفيقالحريري ورشاقه اعتبر يريدون قيامهاءليظل المجرمون يسرحون ويمرحون بكركيوعندما ايدت",
        "sentence_20": "بكركي قيام الحكومه بتصريفالاعمال ريثمايتم انتخاب رئيس للجمهوريه لاتهيجوز تعطيل",
        "sentence_30": "مصالح الناس اعتبر البعض انبكركي تؤيد بقاء الحكومه البعضيريد تعطيل",
        "sentence_40": "شيء لبنان حدهوعندما قال سيد يكركي ان الاكثريهاذا انتقلت الي",
        "sentence_50": "قوي اذار اخطاراواخطاء سيكون وزنها التاريخي مصيرالوطن اعتبر البعض انه",
        "sentence_60": "يقف قوياذار\n"
    },
    "49": {
        "sentence_x0": "واستمجن عدم اعتراض تيار المستقبلالموالين وصمتهم حيالالتقارير الدوليه انهم المقابلاقاموا",
        "sentence_x10": "الدنيا ولم يقعدوها ضد المعارضهو حزب الله مندما اصدرا تصريماتمشابهه",
        "sentence_x20": "تماما لتلك التقارير الدوليه اخيراءمتسائلا ينتظر القاضيان سعيد ميرزاوصقر صقر",
        "sentence_x30": "الادانات الدوليهوالعالميه خصوصا قول القاضيدائيال بلمار ان المجرمين اغتالهاالرئيس رفيق",
        "sentence_x40": "الحريري يزالون احرارا ”شاهدان ملف العريضياستمع قاضي التحقيق العدلي عبدالرحيم",
        "sentence_x50": "حمود امس الي افادتي شاهدينملف جريمه اغتيال الشيخ صالح العريضيبانفجار",
        "sentence_x60": "استهدفه سيارته\n",
        "keywords": "اغتيال,رفيق,الحريري",
        "year": 2009,
        "label": "",
        "sentence_0": "واستمجن عدم اعتراض تيار المستقبلالموالين وصمتهم حيالالتقارير الدوليه انهم المقابلاقاموا",
        "sentence_10": "الدنيا ولم يقعدوها ضد المعارضهو حزب الله مندما اصدرا تصريماتمشابهه",
        "sentence_20": "تماما لتلك التقارير الدوليه اخيراءمتسائلا ينتظر القاضيان سعيد ميرزاوصقر صقر",
        "sentence_30": "الادانات الدوليهوالعالميه خصوصا قول القاضيدائيال بلمار ان المجرمين اغتالهاالرئيس رفيق",
        "sentence_40": "الحريري يزالون احرارا ”شاهدان ملف العريضياستمع قاضي التحقيق العدلي عبدالرحيم",
        "sentence_50": "حمود امس الي افادتي شاهدينملف جريمه اغتيال الشيخ صالح العريضيبانفجار",
        "sentence_60": "استهدفه سيارته\n"
    }
}